src/axi_lite_control.v
// -----------------------------------------------------------------------------
// 文件名: src/axi_lite_control.v
// 版本: 1.2 (Fix reg/assign conflict)
// 描述: AXI4-Lite Slave 控制接口
//       - 修复了 o_soft_rst_n 的类型定义错误
//       - 包含 PPU 量化参数寄存器
// -----------------------------------------------------------------------------

`timescale 1ns / 1ps

module axi_lite_control #(
    parameter C_S_AXI_DATA_WIDTH = 32,
    parameter C_S_AXI_ADDR_WIDTH = 5 
)(
    // --- Global Signals ---
    input  wire                                 clk,
    input  wire                                 rst_n,

    // --- AXI4-Lite Slave Interface ---
    input  wire [C_S_AXI_ADDR_WIDTH-1:0]        s_axi_awaddr,
    input  wire                                 s_axi_awvalid,
    output reg                                  s_axi_awready,
    input  wire [C_S_AXI_DATA_WIDTH-1:0]        s_axi_wdata,
    input  wire [3:0]                           s_axi_wstrb,
    input  wire                                 s_axi_wvalid,
    output reg                                  s_axi_wready,
    output wire [1:0]                           s_axi_bresp,
    output reg                                  s_axi_bvalid,
    input  wire                                 s_axi_bready,
    input  wire [C_S_AXI_ADDR_WIDTH-1:0]        s_axi_araddr,
    input  wire                                 s_axi_arvalid,
    output reg                                  s_axi_arready,
    output reg  [C_S_AXI_DATA_WIDTH-1:0]        s_axi_rdata,
    output wire [1:0]                           s_axi_rresp,
    output reg                                  s_axi_rvalid,
    input  wire                                 s_axi_rready,

    // --- User Interface (To Core) ---
    output reg                                  o_ap_start,            // Pulse, Registered
    output wire                                 o_soft_rst_n,          // [FIX] Changed to wire
    output wire [31:0]                          o_cfg_compute_cycles,  // Wire driven by reg
    output wire                                 o_cfg_acc_mode,        // Wire driven by reg
    input  wire                                 i_ap_done,
    input  wire                                 i_ap_idle,

    // --- User Interface (To PPU) ---
    output wire [15:0]                          o_ppu_mult,
    output wire [4:0]                           o_ppu_shift,
    output wire [7:0]                           o_ppu_zp,
    output wire [31:0]                          o_ppu_bias
);

    // -------------------------------------------------------------------------
    // Register Map
    // -------------------------------------------------------------------------
    localparam ADDR_CTRL_REG    = 5'h00;
    localparam ADDR_STATUS_REG  = 5'h04;
    localparam ADDR_CFG_K       = 5'h08;
    localparam ADDR_CFG_ACC     = 5'h0C;
    localparam ADDR_VERSION     = 5'h10;
    
    // PPU Registers
    localparam ADDR_PPU_MULT    = 5'h14; 
    localparam ADDR_PPU_SHIFT   = 5'h18; 
    localparam ADDR_PPU_ZP      = 5'h1C; 

    localparam VERSION_ID       = 32'h20260117;

    // -------------------------------------------------------------------------
    // Internal Registers
    // -------------------------------------------------------------------------
    reg [31:0] reg_ctrl;
    reg [31:0] reg_status;
    reg [31:0] reg_cfg_k;
    reg [31:0] reg_cfg_acc;
    
    reg [31:0] reg_ppu_mult;
    reg [31:0] reg_ppu_shift;
    reg [31:0] reg_ppu_zp;

    // -------------------------------------------------------------------------
    // AXI Write Channel
    // -------------------------------------------------------------------------
    always @(posedge clk or negedge rst_n) begin
        if (!rst_n) begin
            s_axi_awready <= 0; s_axi_wready <= 0; s_axi_bvalid <= 0;
            reg_ctrl <= 0; reg_cfg_k <= 0; reg_cfg_acc <= 0;
            reg_ppu_mult <= 0; reg_ppu_shift <= 0; reg_ppu_zp <= 0;
            o_ap_start <= 0;
        end else begin
            // Default: Clear Pulse
            if (o_ap_start) o_ap_start <= 0;

            s_axi_awready <= 0; s_axi_wready <= 0;
            
            // Handshake Logic: Wait for both AWVALID and WVALID
            if (!s_axi_awready && !s_axi_wready && s_axi_awvalid && s_axi_wvalid) begin
                s_axi_awready <= 1; s_axi_wready <= 1;
                
                case (s_axi_awaddr[4:2])
                    3'h0: begin // 0x00 CTRL
                        if (s_axi_wstrb[0]) begin
                             if (s_axi_wdata[0]) o_ap_start <= 1; // Trigger Pulse
                             reg_ctrl[1] <= s_axi_wdata[1];       // Soft Reset Level
                        end
                    end
                    3'h1: begin // 0x04 STATUS (W1C for Bit 0)
                        if (s_axi_wstrb[0] && s_axi_wdata[0]) reg_status[0] <= 0;
                    end
                    3'h2: if (s_axi_wstrb[0]) reg_cfg_k <= s_axi_wdata;
                    3'h3: if (s_axi_wstrb[0]) reg_cfg_acc <= s_axi_wdata;
                    
                    // PPU Configs
                    3'h5: if (s_axi_wstrb[0]) reg_ppu_mult <= s_axi_wdata;
                    3'h6: if (s_axi_wstrb[0]) reg_ppu_shift <= s_axi_wdata;
                    3'h7: if (s_axi_wstrb[0]) reg_ppu_zp <= s_axi_wdata;
                endcase
            end

            // Response Logic
            if (s_axi_awready && s_axi_wready) s_axi_bvalid <= 1;
            else if (s_axi_bready && s_axi_bvalid) s_axi_bvalid <= 0;
        end
    end

    assign s_axi_bresp = 2'b00;

    // -------------------------------------------------------------------------
    // Status Register Logic (Sticky Bits)
    // -------------------------------------------------------------------------
    always @(posedge clk or negedge rst_n) begin
        if (!rst_n) reg_status <= 0;
        else begin
            reg_status[1] <= i_ap_idle; // Real-time
            
            // Sticky Done Logic
            if (i_ap_done) reg_status[0] <= 1;
            else if (s_axi_awready && s_axi_wvalid && s_axi_awaddr[4:2] == 3'h1 && s_axi_wdata[0]) 
                reg_status[0] <= 0; // Clear on W1C
        end
    end

    // -------------------------------------------------------------------------
    // AXI Read Channel
    // -------------------------------------------------------------------------
    always @(posedge clk or negedge rst_n) begin
        if (!rst_n) begin
            s_axi_arready <= 0; s_axi_rvalid <= 0; s_axi_rdata <= 0;
        end else begin
            if (!s_axi_arready && s_axi_arvalid) begin
                s_axi_arready <= 1;
                case (s_axi_araddr[4:2])
                    3'h0: s_axi_rdata <= reg_ctrl;
                    3'h1: s_axi_rdata <= reg_status;
                    3'h2: s_axi_rdata <= reg_cfg_k;
                    3'h3: s_axi_rdata <= reg_cfg_acc;
                    3'h4: s_axi_rdata <= VERSION_ID;
                    3'h5: s_axi_rdata <= reg_ppu_mult;
                    3'h6: s_axi_rdata <= reg_ppu_shift;
                    3'h7: s_axi_rdata <= reg_ppu_zp;
                    default: s_axi_rdata <= 0;
                endcase
            end else begin
                s_axi_arready <= 0;
            end

            if (s_axi_arready && s_axi_arvalid) s_axi_rvalid <= 1;
            else if (s_axi_rready && s_axi_rvalid) s_axi_rvalid <= 0;
        end
    end
    assign s_axi_rresp = 2'b00;

    // -------------------------------------------------------------------------
    // Output Assignments
    // -------------------------------------------------------------------------
    // [FIX] These are now wire assignments driven by internal registers
    assign o_soft_rst_n         = reg_ctrl[1];
    assign o_cfg_compute_cycles = reg_cfg_k;
    assign o_cfg_acc_mode       = reg_cfg_acc[0];
    
    assign o_ppu_mult  = reg_ppu_mult[15:0];
    assign o_ppu_shift = reg_ppu_shift[4:0];
    assign o_ppu_zp    = reg_ppu_zp[7:0];
    assign o_ppu_bias  = 0; // Placeholder

endmodule

src/axi_lite_control_tb.v
// -----------------------------------------------------------------------------
// 文件名: src/axi_lite_control_tb.v
// 描述: AXI-Lite 接口自检 Testbench
// -----------------------------------------------------------------------------
`timescale 1ns / 1ps

module axi_lite_control_tb;

    // --- Clock & Reset ---
    reg clk, rst_n;
    always #5 clk = ~clk; // 100MHz

    // --- AXI Interface Signals ---
    reg  [4:0]  s_axi_awaddr;
    reg         s_axi_awvalid;
    wire        s_axi_awready;
    reg  [31:0] s_axi_wdata;
    reg  [3:0]  s_axi_wstrb;
    reg         s_axi_wvalid;
    wire        s_axi_wready;
    wire [1:0]  s_axi_bresp;
    wire        s_axi_bvalid;
    reg         s_axi_bready;
    reg  [4:0]  s_axi_araddr;
    reg         s_axi_arvalid;
    wire        s_axi_arready;
    wire [31:0] s_axi_rdata;
    wire [1:0]  s_axi_rresp;
    wire        s_axi_rvalid;
    reg         s_axi_rready;

    // --- User Signals ---
    wire        o_ap_start;
    wire        o_soft_rst_n;
    wire [31:0] o_cfg_compute_cycles;
    wire        o_cfg_acc_mode;
    reg         i_ap_done;
    reg         i_ap_idle;
    wire [15:0] o_ppu_mult;
    wire [4:0]  o_ppu_shift;
    wire [7:0]  o_ppu_zp;
    wire [31:0] o_ppu_bias;
    // --- DUT Instantiation ---
    axi_lite_control dut (
        .clk(clk), .rst_n(rst_n),
        .s_axi_awaddr(s_axi_awaddr), .s_axi_awvalid(s_axi_awvalid), .s_axi_awready(s_axi_awready),
        .s_axi_wdata(s_axi_wdata), .s_axi_wstrb(s_axi_wstrb), .s_axi_wvalid(s_axi_wvalid), .s_axi_wready(s_axi_wready),
        .s_axi_bresp(s_axi_bresp), .s_axi_bvalid(s_axi_bvalid), .s_axi_bready(s_axi_bready),
        .s_axi_araddr(s_axi_araddr), .s_axi_arvalid(s_axi_arvalid), .s_axi_arready(s_axi_arready),
        .s_axi_rdata(s_axi_rdata), .s_axi_rresp(s_axi_rresp), .s_axi_rvalid(s_axi_rvalid), .s_axi_rready(s_axi_rready),
        .o_ap_start(o_ap_start), .o_soft_rst_n(o_soft_rst_n),
        .o_cfg_compute_cycles(o_cfg_compute_cycles), .o_cfg_acc_mode(o_cfg_acc_mode),
        .i_ap_done(i_ap_done), .i_ap_idle(i_ap_idle),
        .o_ppu_mult(o_ppu_mult), .o_ppu_shift(o_ppu_shift), .o_ppu_zp(o_ppu_zp), .o_ppu_bias(o_ppu_bias)
    
    );

    // --- AXI Tasks (模拟 Master 行为) ---
    task axi_write;
        input [4:0] addr;
        input [31:0] data;
        begin
            @(posedge clk);
            s_axi_awaddr <= addr;
            s_axi_awvalid <= 1;
            s_axi_wdata <= data;
            s_axi_wstrb <= 4'hF;
            s_axi_wvalid <= 1;
            s_axi_bready <= 1;
            
            // Wait for handshake
            wait(s_axi_awready && s_axi_wready);
            @(posedge clk);
            s_axi_awvalid <= 0;
            s_axi_wvalid <= 0;
            
            wait(s_axi_bvalid);
            @(posedge clk);
            s_axi_bready <= 0;
        end
    endtask

    task axi_read;
        input [4:0] addr;
        output [31:0] data;
        begin
            @(posedge clk);
            s_axi_araddr <= addr;
            s_axi_arvalid <= 1;
            s_axi_rready <= 1;
            
            wait(s_axi_arready);
            @(posedge clk);
            s_axi_arvalid <= 0;
            
            wait(s_axi_rvalid);
            data = s_axi_rdata;
            @(posedge clk);
            s_axi_rready <= 0;
        end
    endtask

    // --- Main Verification Flow ---
    reg [31:0] read_val;
    integer err_cnt = 0;

    initial begin
        $dumpfile("axi_lite_verify.vcd");
        $dumpvars(0, axi_lite_control_tb);

        // Init
        clk = 0; rst_n = 0;
        s_axi_awvalid = 0; s_axi_wvalid = 0; s_axi_bready = 0;
        s_axi_arvalid = 0; s_axi_rready = 0;
        i_ap_done = 0; i_ap_idle = 1;

        #20 rst_n = 1;
        #20;

        $display("=== START AXI-LITE VERIFICATION ===");

        // --- CP1: Version Check ---
        axi_read(5'h10, read_val);
        if (read_val === 32'h20260116) $display("[PASS] CP1: Version ID Matches.");
        else begin $display("[FAIL] CP1: Version Mismatch. Got %h", read_val); err_cnt=err_cnt+1; end

        // --- CP2: Config Registers ---
        axi_write(5'h08, 32'd197); // Set K_DIM
        axi_write(5'h0C, 32'd1);   // Set ACC_MODE
        #10;
        if (o_cfg_compute_cycles === 197 && o_cfg_acc_mode === 1) 
            $display("[PASS] CP2: Config Registers Output Correct.");
        else begin $display("[FAIL] CP2: Config Output Error."); err_cnt=err_cnt+1; end

        // --- CP3: Soft Reset Control ---
        axi_write(5'h00, 32'h00000002); // Bit 1 = 1
        #10;
        if (o_soft_rst_n === 1) $display("[PASS] CP3: Soft Reset High.");
        else begin $display("[FAIL] CP3: Soft Reset Failed."); err_cnt=err_cnt+1; end

        // --- CP4: ap_start Auto-Clear ---
        fork
            begin
                axi_write(5'h00, 32'h00000001); // Bit 0 = 1
            end
            begin
                // Monitor output pulse
                wait(o_ap_start == 1);
                @(posedge clk);
                #10;
                if (o_ap_start == 0) $display("[PASS] CP4: ap_start Pulse Auto-Cleared.");
                else begin $display("[FAIL] CP4: ap_start Stuck at 1."); err_cnt=err_cnt+1; end
            end
        join

        // --- CP5: ap_done Sticky & W1C ---
        // Simulate Core Done
        #20 i_ap_done = 1; i_ap_idle = 1;
        #10 i_ap_done = 0; // Pulse ends
        
        // Read Status (Should be 1 even though input pulse is gone)
        axi_read(5'h04, read_val); 
        if (read_val[0] === 1) $display("[PASS] CP5a: ap_done Sticky Bit Set.");
        else begin $display("[FAIL] CP5a: ap_done Sticky Bit Not Set."); err_cnt=err_cnt+1; end

        // Write 1 to Clear
        axi_write(5'h04, 32'h00000001);
        axi_read(5'h04, read_val);
        if (read_val[0] === 0) $display("[PASS] CP5b: ap_done W1C Cleared.");
        else begin $display("[FAIL] CP5b: ap_done Not Cleared."); err_cnt=err_cnt+1; end
        // --- CP6: PPU Config Verification ---
        $display("[TB] CP6: Testing PPU Config Registers...");
        axi_write(5'h14, 32'h0000_0100); // Mult = 256
        axi_write(5'h18, 32'h0000_0008); // Shift = 8
        axi_write(5'h1C, 32'h0000_000A); // ZP = 10
        
        #10;
        if (o_ppu_mult === 256 && o_ppu_shift === 8 && o_ppu_zp === 10) 
            $display("[PASS] CP6: PPU Config Correct.");
        else begin
            $display("[FAIL] CP6: PPU Config Error. Mult=%d, Shift=%d, ZP=%d", o_ppu_mult, o_ppu_shift, o_ppu_zp);
            err_cnt = err_cnt + 1;
        end
        // --- Final Report ---
        if (err_cnt == 0) $display("\n=== SUCCESS: All Checkpoints Passed! ===\n");
        else $display("\n=== FAILURE: Found %0d Errors ===\n", err_cnt);
        
        $finish;
    end

endmodule

axi_lite_verify.vcd
$date
	Fri Jan 16 11:58:24 2026
$end
$version
	Icarus Verilog
$end
$timescale
	1ps
$end
$scope module axi_lite_control_tb $end
$var wire 32 ! o_ppu_bias [31:0] $end
$var wire 2 " s_axi_bresp [1:0] $end
$var wire 2 # s_axi_rresp [1:0] $end
$var wire 1 $ s_axi_wready $end
$var wire 1 % s_axi_rvalid $end
$var wire 32 & s_axi_rdata [31:0] $end
$var wire 1 ' s_axi_bvalid $end
$var wire 1 ( s_axi_awready $end
$var wire 1 ) s_axi_arready $end
$var wire 1 * o_soft_rst_n $end
$var wire 8 + o_ppu_zp [7:0] $end
$var wire 5 , o_ppu_shift [4:0] $end
$var wire 16 - o_ppu_mult [15:0] $end
$var wire 32 . o_cfg_compute_cycles [31:0] $end
$var wire 1 / o_cfg_acc_mode $end
$var wire 1 0 o_ap_start $end
$var reg 1 1 clk $end
$var reg 1 2 i_ap_done $end
$var reg 1 3 i_ap_idle $end
$var reg 32 4 read_val [31:0] $end
$var reg 1 5 rst_n $end
$var reg 5 6 s_axi_araddr [4:0] $end
$var reg 1 7 s_axi_arvalid $end
$var reg 5 8 s_axi_awaddr [4:0] $end
$var reg 1 9 s_axi_awvalid $end
$var reg 1 : s_axi_bready $end
$var reg 1 ; s_axi_rready $end
$var reg 32 < s_axi_wdata [31:0] $end
$var reg 4 = s_axi_wstrb [3:0] $end
$var reg 1 > s_axi_wvalid $end
$var integer 32 ? err_cnt [31:0] $end
$scope module dut $end
$var wire 1 1 clk $end
$var wire 1 2 i_ap_done $end
$var wire 1 3 i_ap_idle $end
$var wire 32 @ o_cfg_compute_cycles [31:0] $end
$var wire 32 A o_ppu_bias [31:0] $end
$var wire 1 5 rst_n $end
$var wire 5 B s_axi_araddr [4:0] $end
$var wire 1 7 s_axi_arvalid $end
$var wire 5 C s_axi_awaddr [4:0] $end
$var wire 1 9 s_axi_awvalid $end
$var wire 1 : s_axi_bready $end
$var wire 2 D s_axi_bresp [1:0] $end
$var wire 1 ; s_axi_rready $end
$var wire 2 E s_axi_rresp [1:0] $end
$var wire 32 F s_axi_wdata [31:0] $end
$var wire 4 G s_axi_wstrb [3:0] $end
$var wire 1 > s_axi_wvalid $end
$var wire 1 * o_soft_rst_n $end
$var wire 8 H o_ppu_zp [7:0] $end
$var wire 5 I o_ppu_shift [4:0] $end
$var wire 16 J o_ppu_mult [15:0] $end
$var wire 1 / o_cfg_acc_mode $end
$var parameter 5 K ADDR_CFG_ACC $end
$var parameter 5 L ADDR_CFG_K $end
$var parameter 5 M ADDR_CTRL_REG $end
$var parameter 5 N ADDR_PPU_MULT $end
$var parameter 5 O ADDR_PPU_SHIFT $end
$var parameter 5 P ADDR_PPU_ZP $end
$var parameter 5 Q ADDR_STATUS_REG $end
$var parameter 5 R ADDR_VERSION $end
$var parameter 32 S C_S_AXI_ADDR_WIDTH $end
$var parameter 32 T C_S_AXI_DATA_WIDTH $end
$var parameter 32 U VERSION_ID $end
$var reg 1 0 o_ap_start $end
$var reg 32 V reg_cfg_acc [31:0] $end
$var reg 32 W reg_cfg_k [31:0] $end
$var reg 32 X reg_ctrl [31:0] $end
$var reg 32 Y reg_ppu_mult [31:0] $end
$var reg 32 Z reg_ppu_shift [31:0] $end
$var reg 32 [ reg_ppu_zp [31:0] $end
$var reg 32 \ reg_status [31:0] $end
$var reg 1 ) s_axi_arready $end
$var reg 1 ( s_axi_awready $end
$var reg 1 ' s_axi_bvalid $end
$var reg 32 ] s_axi_rdata [31:0] $end
$var reg 1 % s_axi_rvalid $end
$var reg 1 $ s_axi_wready $end
$upscope $end
$scope task axi_read $end
$var reg 5 ^ addr [4:0] $end
$var reg 32 _ data [31:0] $end
$upscope $end
$scope task axi_write $end
$var reg 5 ` addr [4:0] $end
$var reg 32 a data [31:0] $end
$upscope $end
$upscope $end
$enddefinitions $end
$comment Show the parameter values. $end
$dumpall
b100000001001100000000100010111 U
b100000 T
b101 S
b10000 R
b100 Q
b11100 P
b11000 O
b10100 N
b0 M
b1000 L
b1100 K
$end
#0
$dumpvars
bx a
bx `
bx _
bx ^
b0 ]
b0 \
b0 [
b0 Z
b0 Y
b0 X
b0 W
b0 V
b0 J
b0 I
b0 H
bx G
bx F
b0 E
b0 D
bx C
bx B
b0 A
b0 @
b0 ?
0>
bx =
bx <
0;
0:
09
bx 8
07
bx 6
05
bx 4
13
02
01
00
0/
b0 .
b0 -
b0 ,
b0 +
0*
0)
0(
0'
b0 &
0%
0$
b0 #
b0 "
b0 !
$end
#5000
11
#10000
01
#15000
11
#20000
01
15
#25000
b10 \
11
#30000
01
#35000
11
#40000
01
b10000 ^
#45000
1;
17
b10000 6
b10000 B
11
#50000
01
#55000
b100000001001100000000100010111 &
b100000001001100000000100010111 ]
1)
11
#60000
01
#65000
b100000001001100000000100010111 _
1%
0)
07
11
#70000
01
#75000
0%
0;
b11000101 a
b1000 `
b1 ?
b100000001001100000000100010111 4
11
#80000
01
#85000
1:
1>
b1111 =
b1111 G
b11000101 <
b11000101 F
19
b1000 8
b1000 C
11
#90000
01
#95000
b11000101 .
b11000101 @
b11000101 W
1$
1(
11
#100000
01
#105000
1'
0$
0(
0>
09
11
#110000
01
#115000
0'
0:
b1 a
b1100 `
11
#120000
01
#125000
1:
1>
b1 <
b1 F
19
b1100 8
b1100 C
11
#130000
01
#135000
1/
b1 V
1$
1(
11
#140000
01
#145000
1'
0$
0(
0>
09
11
#150000
01
#155000
0'
0:
11
#160000
01
#165000
1:
1>
b10 <
b10 F
19
b0 8
b0 C
11
b10 a
b0 `
#170000
01
#175000
1*
b10 X
1$
1(
11
#180000
01
#185000
1'
0$
0(
0>
09
11
#190000
01
#195000
0'
0:
11
#200000
01
#205000
1:
1>
b1 <
b1 F
19
11
b1 a
#210000
01
#215000
0*
b0 X
10
1$
1(
11
#220000
01
#225000
1'
0$
0(
00
0>
09
11
#230000
01
#235000
0'
0:
11
#240000
01
#245000
11
#250000
01
#255000
b11 \
11
12
#260000
01
#265000
1;
17
b100 6
b100 B
11
b100 ^
02
#270000
01
#275000
b11 &
b11 ]
1)
11
#280000
01
#285000
b11 _
1%
0)
07
11
#290000
01
#295000
0%
0;
b100 `
b11 4
11
#300000
01
#305000
1:
1>
19
b100 8
b100 C
11
#310000
01
#315000
b10 \
1$
1(
11
#320000
01
#325000
1'
0$
0(
0>
09
11
#330000
01
#335000
0'
0:
11
#340000
01
#345000
1;
17
11
#350000
01
#355000
b10 &
b10 ]
1)
11
#360000
01
#365000
b10 _
1%
0)
07
11
#370000
01
#375000
0%
0;
b100000000 a
b10100 `
b10 4
11
#380000
01
#385000
1:
1>
b100000000 <
b100000000 F
19
b10100 8
b10100 C
11
#390000
01
#395000
b100000000 -
b100000000 J
b100000000 Y
1$
1(
11
#400000
01
#405000
1'
0$
0(
0>
09
11
#410000
01
#415000
0'
0:
b1000 a
b11000 `
11
#420000
01
#425000
1:
1>
b1000 <
b1000 F
19
b11000 8
b11000 C
11
#430000
01
#435000
b1000 ,
b1000 I
b1000 Z
1$
1(
11
#440000
01
#445000
1'
0$
0(
0>
09
11
#450000
01
#455000
0'
0:
b1010 a
b11100 `
11
#460000
01
#465000
1:
1>
b1010 <
b1010 F
19
b11100 8
b11100 C
11
#470000
01
#475000
b1010 +
b1010 H
b1010 [
1$
1(
11
#480000
01
#485000
1'
0$
0(
0>
09
11
#490000
01
#495000
0'
0:
11
