src/params.vh
// -----------------------------------------------------------------------------
// 文件名: params.vh
// 描述: 定义加速器的全局参数
// -----------------------------------------------------------------------------

`ifndef PARAMS_VH
`define PARAMS_VH

// -----------------------------------------------------------------------------
// 阵列维度定义 (物理维度)
// -----------------------------------------------------------------------------
// 为了适应 Zynq-7020 的 DSP资源 (220个)，我们选择 12x16
// 注意：宏定义不加分号
`define ARRAY_ROW 12
`define ARRAY_COL 16

// -----------------------------------------------------------------------------
// 数据位宽定义
// -----------------------------------------------------------------------------
`define DATA_WIDTH    8
`define ACC_WIDTH     32
`define AXI_DATA_WIDTH 64

// -----------------------------------------------------------------------------
// 默认计数器阈值 (可运行时配置)
// -----------------------------------------------------------------------------
// DeiT-Tiny Hidden Dimension = 192.
// 我们假设每次计算处理一个 Tile 的 K 维度。
`define DEFAULT_K_DIM 192 

`endif

src/input_buffer_ctrl.v
// -----------------------------------------------------------------------------
// 文件名: src/input_buffer_ctrl.v
// 作者: Google FPGA Architect Mentor
// 描述: 输入缓冲控制器 (Fixed for Pipeline Alignment)
// -----------------------------------------------------------------------------

`timescale 1ns / 1ps
`include "params.vh"

module input_buffer_ctrl #(
    parameter DEPTH_LOG2 = 8  
)(
    input  wire                         clk,
    input  wire                         rst_n,

    // --- AXI-Stream Slave Interface ---
    input  wire [63:0]                  s_axis_tdata,
    input  wire                         s_axis_tvalid,
    output wire                         s_axis_tready, 
    input  wire                         s_axis_tlast, 

    // --- Core Interface ---
    input  wire                         i_rd_en,      
    output wire [`ARRAY_ROW*8-1:0]      o_array_vec,   

    // --- Control Interface ---
    input  wire                         i_bank_swap    
);

    // -------------------------------------------------------------------------
    // 1. Ping-Pong State
    // -------------------------------------------------------------------------
    reg bank_sel; 
    
    always @(posedge clk or negedge rst_n) begin
        if (!rst_n) bank_sel <= 0;
        else if (i_bank_swap) bank_sel <= ~bank_sel;
    end

    // -------------------------------------------------------------------------
    // 2. Gearbox Logic (64-bit -> 96-bit)
    // -------------------------------------------------------------------------
    reg [1:0]  gb_state; 
    reg [95:0] ram_wdata;
    reg        ram_wen;
    
    reg [DEPTH_LOG2-1:0] wr_ptr;
    reg [DEPTH_LOG2-1:0] wr_addr_pipe; // FIX: 新增地址流水线寄存器

    reg [63:0] temp_reg;

    assign s_axis_tready = 1'b1; 

    always @(posedge clk or negedge rst_n) begin
        if (!rst_n) begin
            gb_state     <= 0;
            wr_ptr       <= 0;
            wr_addr_pipe <= 0;
            ram_wen      <= 0;
            ram_wdata    <= 0;
            temp_reg     <= 0;
        end else begin
            ram_wen <= 0; // Pulse default low

            if (i_bank_swap) begin
                wr_ptr <= 0;
                gb_state <= 0;
            end
            else if (s_axis_tvalid) begin
                case (gb_state)
                    0: begin 
                        // Word 1: Store only
                        temp_reg <= s_axis_tdata; 
                        gb_state <= 1;
                    end
                    1: begin
                        // Word 2: Output 1 (Low 32 of current + Old 64)
                        ram_wdata <= {s_axis_tdata[31:0], temp_reg};
                        ram_wen   <= 1;
                        
                        // FIX: 记录当前的 wr_ptr 用于下一拍写入
                        wr_addr_pipe <= wr_ptr; 
                        
                        // 指针加 1，为下一次数据做准备
                        wr_ptr    <= wr_ptr + 1;
                        
                        // Store High 32
                        temp_reg[31:0] <= s_axis_tdata[63:32]; 
                        gb_state <= 2;
                    end
                    2: begin
                        // Word 3: Output 2 (Current 64 + Old 32)
                        ram_wdata <= {s_axis_tdata, temp_reg[31:0]};
                        ram_wen   <= 1;
                        
                        // FIX: 记录当前的 wr_ptr
                        wr_addr_pipe <= wr_ptr;
                        
                        wr_ptr    <= wr_ptr + 1;
                        
                        gb_state <= 0; 
                    end
                endcase
            end
        end
    end

    // -------------------------------------------------------------------------
    // 3. Memory Inference
    // -------------------------------------------------------------------------
    reg [95:0] ram [0:(1<<(DEPTH_LOG2+1))-1]; 
    
    // FIX: 使用 wr_addr_pipe 而不是 wr_ptr
    // 这样，当 ram_wen 在下一拍生效时，地址也是上一拍锁存下来的正确地址 (0)
    // 而不是已经自增后的新地址 (1)
    wire [DEPTH_LOG2:0] final_wr_addr = {bank_sel, wr_addr_pipe}; 
    
    always @(posedge clk) begin
        if (ram_wen) begin
            ram[final_wr_addr] <= ram_wdata;
        end
    end

    // --- Read Port ---
    reg [DEPTH_LOG2-1:0] rd_ptr;
    wire [DEPTH_LOG2:0] final_rd_addr = {~bank_sel, rd_ptr}; 
    reg [95:0] ram_out_reg;

    always @(posedge clk or negedge rst_n) begin
        if (!rst_n) begin
            rd_ptr <= 0;
        end else begin
            if (i_bank_swap) begin
                rd_ptr <= 0; 
            end else if (i_rd_en) begin
                rd_ptr <= rd_ptr + 1;
            end
        end
    end
    
    always @(posedge clk) begin
        ram_out_reg <= ram[final_rd_addr];
    end

    assign o_array_vec = ram_out_reg;

endmodule

src/input_buffer_ctrl_tb.v
// -----------------------------------------------------------------------------
// 文件名: src/input_buffer_ctrl_tb.v
// 描述: 验证 Gearbox 和 Ping-Pong 逻辑
// -----------------------------------------------------------------------------
`timescale 1ns / 1ps

module input_buffer_ctrl_tb;

    reg clk, rst_n;
    reg [63:0] s_axis_tdata;
    reg s_axis_tvalid, s_axis_tlast;
    wire s_axis_tready;
    
    reg i_rd_en;
    wire [95:0] o_array_vec;
    reg i_bank_swap;

    // DUT
    input_buffer_ctrl dut (
        .clk(clk), .rst_n(rst_n),
        .s_axis_tdata(s_axis_tdata), .s_axis_tvalid(s_axis_tvalid), 
        .s_axis_tready(s_axis_tready), .s_axis_tlast(s_axis_tlast),
        .i_rd_en(i_rd_en), .o_array_vec(o_array_vec),
        .i_bank_swap(i_bank_swap)
    );

    always #5 clk = ~clk;

    // Helper task to send 64-bit word
    task send_word;
        input [63:0] data;
        begin
            s_axis_tdata <= data;
            s_axis_tvalid <= 1;
            @(posedge clk);
            // wait for ready if we implemented flow control (we didn't yet)
            s_axis_tvalid <= 0;
        end
    endtask

    integer err_cnt = 0;

    initial begin
        $dumpfile("buffer_verify.vcd");
        $dumpvars(0, input_buffer_ctrl_tb);

        clk = 0; rst_n = 0;
        s_axis_tdata = 0; s_axis_tvalid = 0; s_axis_tlast = 0;
        i_rd_en = 0; i_bank_swap = 0;

        #20 rst_n = 1;
        #20;

        $display("=== START BUFFER VERIFICATION ===");

        // ---------------------------------------------------------
        // CP1: Write to Bank 0 (Gearbox Test)
        // ---------------------------------------------------------
        // We want to write 2 vectors of 96-bit (Total 192 bits).
        // This requires 3 writes of 64-bit.
        // Data Pattern: 
        // Word 1: 0x11111111_00000000 (Hi_Lo)
        // Word 2: 0x33333333_22222222
        // Word 3: 0x55555555_44444444
        //
        // Expected RAM Content:
        // Vec 0 (96b): {22222222, 11111111, 00000000} (Little Endian Assembly)
        // Vec 1 (96b): {55555555, 44444444, 33333333}
        
        $display("[TB] Writing 3x64-bit words to Bank 0...");
        
        // Initial State: Bank Sel = 0 (Write 0, Read 1)
        send_word(64'h11111111_00000000); // 1st
        send_word(64'h33333333_22222222); // 2nd -> Should trigger RAM Write 0
        send_word(64'h55555555_44444444); // 3rd -> Should trigger RAM Write 1

        #20;
        
        // ---------------------------------------------------------
        // CP2: Ping-Pong Swap & Read Verification
        // ---------------------------------------------------------
        $display("[TB] Swapping Banks...");
        @(posedge clk);
        i_bank_swap = 1; // Toggle: Now Write 1, Read 0
        @(posedge clk);
        i_bank_swap = 0;

        $display("[TB] Reading from Bank 0...");
        // Read 0
        i_rd_en = 1;
        @(posedge clk); // Latency 1 (Address setup)
        @(posedge clk); // Latency 2 (Data out)
        
        // Check Vec 0
        // Expect: 0x22222222_11111111_00000000
        if (o_array_vec === 96'h22222222_11111111_00000000) 
            $display("[PASS] CP2a: Vec 0 Data Match.");
        else begin
            $display("[FAIL] CP2a: Expected 22..11..00, Got %h", o_array_vec);
            err_cnt = err_cnt + 1;
        end

        // Read 1
        @(posedge clk); 
        // Check Vec 1
        // Expect: 0x55555555_44444444_33333333
        if (o_array_vec === 96'h55555555_44444444_33333333) 
            $display("[PASS] CP2b: Vec 1 Data Match.");
        else begin
            $display("[FAIL] CP2b: Expected 55..44..33, Got %h", o_array_vec);
            err_cnt = err_cnt + 1;
        end
        
        i_rd_en = 0;

        // ---------------------------------------------------------
        // CP3: Concurrent Read/Write (Ping-Pong Safety)
        // ---------------------------------------------------------
        // Now we are Reading Bank 0. Let's Write to Bank 1 simultaneously.
        // It should NOT corrupt Bank 0 reading (if we were still reading).
        // Let's write Full 1s to Bank 1.
        $display("[TB] Writing to Bank 1 while Bank 0 is active for read...");
        send_word({64{1'b1}});
        send_word({64{1'b1}});
        send_word({64{1'b1}});
        
        // Swap to read Bank 1
        @(posedge clk);
        i_bank_swap = 1; // Now Read 1, Write 0
        @(posedge clk);
        i_bank_swap = 0;
        
        i_rd_en = 1;
        @(posedge clk);
        @(posedge clk);
        
        if (o_array_vec === {96{1'b1}})
             $display("[PASS] CP3: Bank 1 Written Correctly.");
        else begin
             $display("[FAIL] CP3: Bank 1 Data Mismatch. Got %h", o_array_vec);
             err_cnt = err_cnt + 1;
        end

        // --- Final Report ---
        if (err_cnt == 0) $display("\n=== SUCCESS: All Checkpoints Passed! ===\n");
        else $display("\n=== FAILURE: Found %0d Errors ===\n", err_cnt);
        $finish;
    end

endmodule

buffer_verify.vcd
$date
	Fri Jan 16 10:58:38 2026
$end
$version
	Icarus Verilog
$end
$timescale
	1ps
$end
$scope module input_buffer_ctrl_tb $end
$var wire 1 ! s_axis_tready $end
$var wire 96 " o_array_vec [95:0] $end
$var reg 1 # clk $end
$var reg 1 $ i_bank_swap $end
$var reg 1 % i_rd_en $end
$var reg 1 & rst_n $end
$var reg 64 ' s_axis_tdata [63:0] $end
$var reg 1 ( s_axis_tlast $end
$var reg 1 ) s_axis_tvalid $end
$var integer 32 * err_cnt [31:0] $end
$scope module dut $end
$var wire 1 # clk $end
$var wire 1 $ i_bank_swap $end
$var wire 1 % i_rd_en $end
$var wire 96 + o_array_vec [95:0] $end
$var wire 1 & rst_n $end
$var wire 64 , s_axis_tdata [63:0] $end
$var wire 1 ( s_axis_tlast $end
$var wire 1 ! s_axis_tready $end
$var wire 1 ) s_axis_tvalid $end
$var wire 9 - final_wr_addr [8:0] $end
$var wire 9 . final_rd_addr [8:0] $end
$var parameter 32 / DEPTH_LOG2 $end
$var reg 1 0 bank_sel $end
$var reg 2 1 gb_state [1:0] $end
$var reg 96 2 ram_out_reg [95:0] $end
$var reg 96 3 ram_wdata [95:0] $end
$var reg 1 4 ram_wen $end
$var reg 8 5 rd_ptr [7:0] $end
$var reg 64 6 temp_reg [63:0] $end
$var reg 8 7 wr_addr_pipe [7:0] $end
$var reg 8 8 wr_ptr [7:0] $end
$upscope $end
$scope task send_word $end
$var reg 64 9 data [63:0] $end
$upscope $end
$upscope $end
$enddefinitions $end
$comment Show the parameter values. $end
$dumpall
b1000 /
$end
#0
$dumpvars
bx 9
b0 8
b0 7
b0 6
b0 5
04
b0 3
bx 2
b0 1
00
b100000000 .
b0 -
b0 ,
bx +
b0 *
0)
0(
b0 '
0&
0%
0$
0#
bx "
1!
$end
#5000
1#
#10000
0#
#15000
1#
#20000
0#
1&
#25000
1#
#30000
0#
#35000
1#
#40000
1)
b1000100010001000100010001000100000000000000000000000000000000 '
b1000100010001000100010001000100000000000000000000000000000000 ,
0#
b1000100010001000100010001000100000000000000000000000000000000 9
#45000
b11001100110011001100110011001100100010001000100010001000100010 '
b11001100110011001100110011001100100010001000100010001000100010 ,
1)
b1 1
b1000100010001000100010001000100000000000000000000000000000000 6
b11001100110011001100110011001100100010001000100010001000100010 9
1#
#50000
0#
#55000
b101010101010101010101010101010101000100010001000100010001000100 '
b101010101010101010101010101010101000100010001000100010001000100 ,
1)
b10 1
b1000100010001000100010001000100110011001100110011001100110011 6
b1 8
14
b1000100010001000100010001000100001000100010001000100010001000100000000000000000000000000000000 3
b101010101010101010101010101010101000100010001000100010001000100 9
1#
#60000
0#
#65000
0)
b0 1
b10 8
b1 -
b1 7
b10101010101010101010101010101010100010001000100010001000100010000110011001100110011001100110011 3
14
1#
#70000
0#
#75000
04
1#
#80000
0#
#85000
1$
1#
#90000
0#
#95000
b0 .
b100000001 -
10
b0 8
1%
0$
1#
#100000
0#
#105000
b1000100010001000100010001000100001000100010001000100010001000100000000000000000000000000000000 "
b1000100010001000100010001000100001000100010001000100010001000100000000000000000000000000000000 +
b1000100010001000100010001000100001000100010001000100010001000100000000000000000000000000000000 2
b1 .
b1 5
1#
#110000
0#
#115000
b10101010101010101010101010101010100010001000100010001000100010000110011001100110011001100110011 "
b10101010101010101010101010101010100010001000100010001000100010000110011001100110011001100110011 +
b10101010101010101010101010101010100010001000100010001000100010000110011001100110011001100110011 2
b10 .
b10 5
1#
#120000
0#
#125000
1)
b1111111111111111111111111111111111111111111111111111111111111111 '
b1111111111111111111111111111111111111111111111111111111111111111 ,
bx "
bx +
bx 2
b11 .
b11 5
b1111111111111111111111111111111111111111111111111111111111111111 9
0%
1#
#130000
0#
#135000
1)
b1 1
b1111111111111111111111111111111111111111111111111111111111111111 6
1#
#140000
0#
#145000
1)
b10 1
b1 8
b100000000 -
b0 7
14
b111111111111111111111111111111111111111111111111111111111111111111111111111111111111111111111111 3
1#
#150000
0#
#155000
0)
b0 1
b10 8
b100000001 -
b1 7
14
1#
#160000
0#
#165000
04
1$
1#
#170000
0#
#175000
b1 -
00
b0 8
b100000000 .
b0 5
1%
0$
1#
#180000
0#
#185000
b111111111111111111111111111111111111111111111111111111111111111111111111111111111111111111111111 "
b111111111111111111111111111111111111111111111111111111111111111111111111111111111111111111111111 +
b111111111111111111111111111111111111111111111111111111111111111111111111111111111111111111111111 2
b100000001 .
b1 5
1#
#190000
0#
#195000
b100000010 .
b10 5
1#
