src/params.vh
// -----------------------------------------------------------------------------
// 文件名: params.vh
// 描述: 定义加速器的全局参数
// -----------------------------------------------------------------------------

`ifndef PARAMS_VH
`define PARAMS_VH

// -----------------------------------------------------------------------------
// 阵列维度定义 (物理维度)
// -----------------------------------------------------------------------------
// 为了适应 Zynq-7020 的 DSP资源 (220个)，我们选择 12x16
// 注意：宏定义不加分号
`define ARRAY_ROW 12
`define ARRAY_COL 16

// -----------------------------------------------------------------------------
// 数据位宽定义
// -----------------------------------------------------------------------------
`define DATA_WIDTH    8
`define ACC_WIDTH     32
`define AXI_DATA_WIDTH 64

// -----------------------------------------------------------------------------
// 默认计数器阈值 (可运行时配置)
// -----------------------------------------------------------------------------
// DeiT-Tiny Hidden Dimension = 192.
// 我们假设每次计算处理一个 Tile 的 K 维度。
`define DEFAULT_K_DIM 192 

`endif

src/global_controller.v
// -----------------------------------------------------------------------------
// 文件名: src/global_controller.v
// 版本: 2.0 (Added DRAIN State for Pipeline Management)
// 作者: Google FPGA Architect Mentor
// 描述: 全局主控制器
//       - 支持 Weight Loading -> Streaming Computation -> Pipeline Draining
//       - 适配 Batch Mode (全序列流式处理)
// -----------------------------------------------------------------------------

`timescale 1ns / 1ps
`include "params.vh"
module global_controller #(
    // Pipeline Latency: 必须与 deit_core 的 LATENCY_CFG 匹配
    // 默认 28, 但为了保险起见，或者更灵活，可以由外部参数覆盖
    parameter LATENCY = 28
)(
    input  wire         clk,
    input  wire         rst_n,

    // --- Control Interface (AXI-Lite) ---
    input  wire         ap_start,
    input  wire [31:0]  cfg_seq_len, // 原 cfg_k_dim, 现更名为 cfg_seq_len (M维度)
    
    output reg          ap_done,
    output reg          ap_idle,

    // --- Status Debug ---
    output wire [2:0]   current_state_dbg,

    // --- Core Control Signals ---
    output reg          ctrl_weight_load_en,  // To Weight Buffer & Array
    output reg          ctrl_input_stream_en, // To Input Buffer
    output reg          ctrl_drain_en         // (Optional) 指示排空状态
);

    // -------------------------------------------------------------------------
    // FSM State Definition
    // -------------------------------------------------------------------------
    localparam S_IDLE     = 3'd0;
    localparam S_LOAD_W   = 3'd1; // Load Weights (12 cycles min)
    localparam S_COMPUTE  = 3'd2; // Stream Inputs (cfg_seq_len cycles)
    localparam S_DRAIN    = 3'd3; // Drain Pipeline (LATENCY cycles)
    localparam S_DONE     = 3'd4; // Pulse ap_done

    reg [2:0] state, next_state;

    // -------------------------------------------------------------------------
    // Counters
    // -------------------------------------------------------------------------
    reg [31:0] cnt_load;
    reg [31:0] cnt_seq;
    reg [31:0] cnt_drain;

    // 12 rows to load, but let's give it 16 cycles for safety/alignment
    localparam LOAD_CYCLES = 24; 

    // -------------------------------------------------------------------------
    // State Register
    // -------------------------------------------------------------------------
    always @(posedge clk or negedge rst_n) begin
        if (!rst_n) state <= S_IDLE;
        else        state <= next_state;
    end

    // -------------------------------------------------------------------------
    // Next State Logic
    // -------------------------------------------------------------------------
    always @(*) begin
        next_state = state;
        case (state)
            S_IDLE: begin
                if (ap_start) next_state = S_LOAD_W;
            end

            S_LOAD_W: begin
                // Load weight rows into array
                if (cnt_load >= LOAD_CYCLES - 1) 
                    next_state = S_COMPUTE;
            end

            S_COMPUTE: begin
                // Stream input vectors (M dimension)
                // If cfg_seq_len is 0 (invalid), jump to done or handle gracefully
                if (cnt_seq >= cfg_seq_len - 1) 
                    next_state = S_DRAIN;
            end

            S_DRAIN: begin
                // Wait for the last input to travel through the array & adder
                if (cnt_drain >= LATENCY - 1) 
                    next_state = S_DONE;
            end

            S_DONE: begin
                // Single cycle pulse
                next_state = S_IDLE;
            end
            
            default: next_state = S_IDLE;
        endcase
    end

    // -------------------------------------------------------------------------
    // Output Logic & Counters
    // -------------------------------------------------------------------------
    always @(posedge clk or negedge rst_n) begin
        if (!rst_n) begin
            ctrl_weight_load_en  <= 0;
            ctrl_input_stream_en <= 0;
            ctrl_drain_en        <= 0;
            ap_done              <= 0;
            ap_idle              <= 1;
            
            cnt_load  <= 0;
            cnt_seq   <= 0;
            cnt_drain <= 0;
        end else begin
            // Default Values
            ctrl_weight_load_en  <= 0;
            ctrl_input_stream_en <= 0;
            ctrl_drain_en        <= 0;
            ap_done              <= 0;
            ap_idle              <= 0; // Busy by default unless in IDLE

            // case (next_state) // Look ahead for cleaner outputs or use current state
            //     // Note: Using 'state' for output logic usually incurs 1 cycle delay 
            //     // vs state transition. For controllers, this is fine or preferred.
            //     // Let's use current 'state' logic inside the clocked block.
            // endcase

            // Re-implementing logic based on CURRENT state for robustness
            case (state)
                S_IDLE: begin
                    ap_idle   <= 1;
                    cnt_load  <= 0;
                    cnt_seq   <= 0;
                    cnt_drain <= 0;
                end

                S_LOAD_W: begin
                    ctrl_weight_load_en <= 1; // ACTIVE
                    cnt_load <= cnt_load + 1;
                end

                S_COMPUTE: begin
                    ctrl_input_stream_en <= 1; // ACTIVE: Input Buffer Reads
                    cnt_seq <= cnt_seq + 1;
                end

                S_DRAIN: begin
                    ctrl_drain_en <= 1; // Status indicator (optional)
                    // Input stream is OFF (ctrl_input_stream_en = 0)
                    // This stops new data from entering, effectively feeding '0's 
                    // if the core logic handles enable low correctly.
                    cnt_drain <= cnt_drain + 1;
                end

                S_DONE: begin
                    ap_done <= 1;
                end
            endcase
        end
    end

    assign current_state_dbg = state;

endmodule

src/global_controller_tb.v
// -----------------------------------------------------------------------------
// 文件名: src/global_controller_tb.v
// 描述: 验证 Global Controller v2.0 的状态流转
// -----------------------------------------------------------------------------
`timescale 1ns / 1ps

module global_controller_tb;

    reg clk, rst_n;
    reg ap_start;
    reg [31:0] cfg_seq_len;
    
    wire ap_done;
    wire ap_idle;
    wire [2:0] current_state_dbg;
    
    wire ctrl_weight_load_en;
    wire ctrl_input_stream_en;
    wire ctrl_drain_en;

    // 参数设置
    localparam LATENCY = 10; // 缩短 Latency 方便仿真波形查看
    
    global_controller #(
        .LATENCY(LATENCY)
    ) dut (
        .clk(clk), .rst_n(rst_n),
        .ap_start(ap_start), .cfg_seq_len(cfg_seq_len),
        .ap_done(ap_done), .ap_idle(ap_idle),
        .current_state_dbg(current_state_dbg),
        .ctrl_weight_load_en(ctrl_weight_load_en),
        .ctrl_input_stream_en(ctrl_input_stream_en),
        .ctrl_drain_en(ctrl_drain_en)
    );

    always #5 clk = ~clk;

    initial begin
        $dumpfile("controller_verify.vcd");
        $dumpvars(0, global_controller_tb);

        clk = 0; rst_n = 0; ap_start = 0; cfg_seq_len = 0;
        #20 rst_n = 1;
        #20;

        $display("=== START CONTROLLER VERIFICATION ===");

        // --- Case 1: Short Sequence (M=32) ---
        $display("[TB] Testing Sequence Length M=32...");
        cfg_seq_len = 32;
        
        @(posedge clk);
        ap_start = 1;
        @(posedge clk);
        ap_start = 0;

        // 1. Wait for Load to finish
        wait(ctrl_weight_load_en == 1);
        $display("[INFO] Entered LOAD State.");
        wait(ctrl_weight_load_en == 0);
        $display("[INFO] LOAD Finished.");

        // 2. Check Compute Duration
        if (ctrl_input_stream_en !== 1) begin
            $display("[FAIL] Compute did not start immediately after Load.");
        end else begin
            $display("[INFO] Entered COMPUTE State.");
        end

        // Measure duration
        fork : timeout_block
            begin
                wait(ctrl_input_stream_en == 0);
                $display("[INFO] COMPUTE Finished (Stream Enable Low).");
                disable timeout_block;
            end
            begin
                #1000; // Timeout
                $display("[FAIL] Timeout waiting for compute to finish.");
                $finish;
            end
        join

        // 3. Check Drain State
        // In Drain state, input stream should be 0, drain_en should be 1
        if (ctrl_drain_en !== 1) $display("[FAIL] Drain Enable not asserted.");
        else $display("[INFO] Entered DRAIN State.");

        // 4. Wait for Done
        wait(ap_done == 1);
        $display("[PASS] ap_done received.");
        
        @(posedge clk);
        if (ap_idle !== 1) $display("[FAIL] Should return to IDLE.");
        else $display("[PASS] Returned to IDLE.");

        $display("\n=== SUCCESS: Controller Logic Verified ===\n");
        $finish;
    end

endmodule

controller_verify.vcd
$date
	Fri Jan 16 16:12:35 2026
$end
$version
	Icarus Verilog
$end
$timescale
	1ps
$end
$scope module global_controller_tb $end
$var wire 3 ! current_state_dbg [2:0] $end
$var wire 1 " ctrl_weight_load_en $end
$var wire 1 # ctrl_input_stream_en $end
$var wire 1 $ ctrl_drain_en $end
$var wire 1 % ap_idle $end
$var wire 1 & ap_done $end
$var parameter 32 ' LATENCY $end
$var reg 1 ( ap_start $end
$var reg 32 ) cfg_seq_len [31:0] $end
$var reg 1 * clk $end
$var reg 1 + rst_n $end
$scope module dut $end
$var wire 1 ( ap_start $end
$var wire 32 , cfg_seq_len [31:0] $end
$var wire 1 * clk $end
$var wire 3 - current_state_dbg [2:0] $end
$var wire 1 + rst_n $end
$var parameter 32 . LATENCY $end
$var parameter 32 / LOAD_CYCLES $end
$var parameter 3 0 S_COMPUTE $end
$var parameter 3 1 S_DONE $end
$var parameter 3 2 S_DRAIN $end
$var parameter 3 3 S_IDLE $end
$var parameter 3 4 S_LOAD_W $end
$var reg 1 & ap_done $end
$var reg 1 % ap_idle $end
$var reg 32 5 cnt_drain [31:0] $end
$var reg 32 6 cnt_load [31:0] $end
$var reg 32 7 cnt_seq [31:0] $end
$var reg 1 $ ctrl_drain_en $end
$var reg 1 # ctrl_input_stream_en $end
$var reg 1 " ctrl_weight_load_en $end
$var reg 3 8 next_state [2:0] $end
$var reg 3 9 state [2:0] $end
$upscope $end
$scope fork timeout_block $end
$upscope $end
$upscope $end
$enddefinitions $end
$comment Show the parameter values. $end
$dumpall
b1 4
b0 3
b11 2
b100 1
b10 0
b10000 /
b1010 .
b1010 '
$end
#0
$dumpvars
b0 9
b0 8
b0 7
b0 6
b0 5
b0 -
b0 ,
0+
0*
b0 )
0(
0&
1%
0$
0#
0"
b0 !
$end
#5000
1*
#10000
0*
#15000
1*
#20000
0*
1+
#25000
1%
1*
#30000
0*
#35000
1%
1*
#40000
0*
b100000 )
b100000 ,
#45000
1%
b1 8
1(
1*
#50000
0*
#55000
b1 !
b1 -
b1 9
1%
b1 8
0(
1*
#60000
0*
#65000
b1 6
1"
0%
1*
#70000
0*
#75000
b10 6
1"
1*
#80000
0*
#85000
b11 6
1"
1*
#90000
0*
#95000
b100 6
1"
1*
#100000
0*
#105000
b101 6
1"
1*
#110000
0*
#115000
b110 6
1"
1*
#120000
0*
#125000
b111 6
1"
1*
#130000
0*
#135000
b1000 6
1"
1*
#140000
0*
#145000
b1001 6
1"
1*
#150000
0*
#155000
b1010 6
1"
1*
#160000
0*
#165000
b1011 6
1"
1*
#170000
0*
#175000
b1100 6
1"
1*
#180000
0*
#185000
b1101 6
1"
1*
#190000
0*
#195000
b1110 6
1"
1*
#200000
0*
#205000
b10 8
b1111 6
1"
1*
#210000
0*
#215000
b10 !
b10 -
b10 9
b10000 6
1"
1*
#220000
0*
#225000
b1 7
1#
0"
1*
#230000
0*
#235000
b10 7
1#
1*
#240000
0*
#245000
b11 7
1#
1*
#250000
0*
#255000
b100 7
1#
1*
#260000
0*
#265000
b101 7
1#
1*
#270000
0*
#275000
b110 7
1#
1*
#280000
0*
#285000
b111 7
1#
1*
#290000
0*
#295000
b1000 7
1#
1*
#300000
0*
#305000
b1001 7
1#
1*
#310000
0*
#315000
b1010 7
1#
1*
#320000
0*
#325000
b1011 7
1#
1*
#330000
0*
#335000
b1100 7
1#
1*
#340000
0*
#345000
b1101 7
1#
1*
#350000
0*
#355000
b1110 7
1#
1*
#360000
0*
#365000
b1111 7
1#
1*
#370000
0*
#375000
b10000 7
1#
1*
#380000
0*
#385000
b10001 7
1#
1*
#390000
0*
#395000
b10010 7
1#
1*
#400000
0*
#405000
b10011 7
1#
1*
#410000
0*
#415000
b10100 7
1#
1*
#420000
0*
#425000
b10101 7
1#
1*
#430000
0*
#435000
b10110 7
1#
1*
#440000
0*
#445000
b10111 7
1#
1*
#450000
0*
#455000
b11000 7
1#
1*
#460000
0*
#465000
b11001 7
1#
1*
#470000
0*
#475000
b11010 7
1#
1*
#480000
0*
#485000
b11011 7
1#
1*
#490000
0*
#495000
b11100 7
1#
1*
#500000
0*
#505000
b11101 7
1#
1*
#510000
0*
#515000
b11110 7
1#
1*
#520000
0*
#525000
b11 8
b11111 7
1#
1*
#530000
0*
#535000
b11 !
b11 -
b11 9
b100000 7
1#
1*
#540000
0*
#545000
b1 5
1$
0#
1*
#550000
0*
#555000
b10 5
1$
1*
#560000
0*
#565000
b11 5
1$
1*
#570000
0*
#575000
b100 5
1$
1*
#580000
0*
#585000
b101 5
1$
1*
#590000
0*
#595000
b110 5
1$
1*
#600000
0*
#605000
b111 5
1$
1*
#610000
0*
#615000
b1000 5
1$
1*
#620000
0*
#625000
b100 8
b1001 5
1$
1*
#630000
0*
#635000
b0 8
b100 !
b100 -
b100 9
b1010 5
1$
1*
#640000
0*
#645000
1&
0$
b0 !
b0 -
b0 9
1*
#650000
0*
#655000
b0 5
b0 7
b0 6
1%
0&
1*
