src/params.vh
// -----------------------------------------------------------------------------
// 文件名: params.vh
// 描述: 定义加速器的全局参数
// -----------------------------------------------------------------------------

`ifndef PARAMS_VH
`define PARAMS_VH

// -----------------------------------------------------------------------------
// 阵列维度定义 (物理维度)
// -----------------------------------------------------------------------------
// 为了适应 Zynq-7020 的 DSP资源 (220个)，我们选择 12x16
// 注意：宏定义不加分号
`define ARRAY_ROW 12
`define ARRAY_COL 16

// -----------------------------------------------------------------------------
// 数据位宽定义
// -----------------------------------------------------------------------------
`define DATA_WIDTH    8
`define ACC_WIDTH     32
`define AXI_DATA_WIDTH 64

// -----------------------------------------------------------------------------
// 默认计数器阈值 (可运行时配置)
// -----------------------------------------------------------------------------
// DeiT-Tiny Hidden Dimension = 192.
// 我们假设每次计算处理一个 Tile 的 K 维度。
`define DEFAULT_K_DIM 192 

`endif

src/ppu.v
// -----------------------------------------------------------------------------
// 文件名: src/ppu.v
// 版本: 1.2 (Added Bias Addition)
// 描述: 量化后处理单元 (INT32 -> INT8)
//       Formula: Clamp( ((Input + Bias) * Mult >> Shift) + ZP )
// -----------------------------------------------------------------------------

`timescale 1ns / 1ps
`include "params.vh"

module ppu (
    input  wire                         clk,
    input  wire                         rst_n,

    // --- Data Path ---
    input  wire                         i_valid,
    input  wire [`ARRAY_COL*32-1:0]     i_data_vec, // 16 x INT32

    output reg                          o_valid,
    output wire [`ARRAY_COL*8-1:0]      o_data_vec, // 16 x INT8

    // --- Configuration (From AXI-Lite) ---
    input  wire [15:0]                  cfg_mult,   // Fixed-point multiplier
    input  wire [4:0]                   cfg_shift,  // Right shift (0..31)
    input  wire [7:0]                   cfg_zp,     // Zero Point
    input  wire [31:0]                  cfg_bias    // Bias (INT32) - NEW
);

    genvar i;
    generate
        for (i = 0; i < `ARRAY_COL; i = i + 1) begin : PPU_LANE
            
            // 1. Unpack Input
            wire signed [31:0] in_val;
            assign in_val = i_data_vec[(i*32) +: 32];

            // -----------------------------------------------------------------
            // 2. Combinational Arithmetic Chain
            // -----------------------------------------------------------------
            
            // Step 0: Add Bias (INT32 + INT32) - NEW
            // 这一步必须在乘法之前，因为 Bias 也是 Accumulator 域的值
            wire signed [31:0] val_biased;
            assign val_biased = in_val + $signed(cfg_bias);

            // Step A: Multiply (32-bit * 16-bit = 48-bit)
            wire signed [47:0] product;
            assign product = val_biased * $signed(cfg_mult);

            // Step B: Shift
            wire signed [47:0] shifted;
            assign shifted = product >>> cfg_shift;

            // Step C: Add Zero Point
            wire signed [47:0] with_zp;
            assign with_zp = shifted + $signed({ {40{1'b0}}, cfg_zp });

            // Step D: Clamp to INT8 [-128, 127]
            wire signed [7:0] clamped_val;
            assign clamped_val = (with_zp > 48'sd127)  ? 8'sd127 :
                                 (with_zp < -48'sd128) ? -8'sd128 :
                                 with_zp[7:0];

            // -----------------------------------------------------------------
            // 3. Pipeline Register
            // -----------------------------------------------------------------
            reg signed [7:0] out_reg;
            
            always @(posedge clk or negedge rst_n) begin
                if (!rst_n) begin
                    out_reg <= 0;
                end else if (i_valid) begin
                    out_reg <= clamped_val;
                end
            end

            // 4. Pack Output
            assign o_data_vec[(i*8) +: 8] = out_reg;

        end
    endgenerate

    // Valid Pipeline
    always @(posedge clk or negedge rst_n) begin
        if (!rst_n) o_valid <= 0;
        else        o_valid <= i_valid;
    end

endmodule

src/ppu_tb.v
// -----------------------------------------------------------------------------
// 文件名: src/ppu_tb.v
// 描述: PPU 验证平台 (Support Bias)
// -----------------------------------------------------------------------------
`timescale 1ns / 1ps
`include "params.vh"

module ppu_tb;

    localparam NUM_TESTS = 100;

    reg clk, rst_n;
    reg i_valid;
    reg [`ARRAY_COL*32-1:0] i_data_vec;
    wire o_valid;
    wire [`ARRAY_COL*8-1:0] o_data_vec;

    reg [15:0] cfg_mult;
    reg [4:0]  cfg_shift;
    reg [7:0]  cfg_zp;
    reg [31:0] cfg_bias; // NEW

    // Memories
    reg [`ARRAY_COL*32-1:0] mem_inputs [0:NUM_TESTS-1];
    reg [`ARRAY_COL*8-1:0]  mem_golden [0:NUM_TESTS-1];
    reg [31:0]              mem_config [0:3]; // Increased size for Bias

    ppu dut (
        .clk(clk), .rst_n(rst_n),
        .i_valid(i_valid), .i_data_vec(i_data_vec),
        .o_valid(o_valid), .o_data_vec(o_data_vec),
        .cfg_mult(cfg_mult), .cfg_shift(cfg_shift), .cfg_zp(cfg_zp),
        .cfg_bias(cfg_bias) // NEW
    );

    always #5 clk = ~clk;

    // Helper
    function signed [7:0] get_byte;
        input [`ARRAY_COL*8-1:0] vec;
        input integer idx;
        begin
            get_byte = vec[(idx*8) +: 8];
        end
    endfunction

    integer i, lane, err_count = 0;

    initial begin
        $dumpfile("ppu_verify.vcd");
        $dumpvars(0, ppu_tb);

        // Load Data
        if (!$test$plusargs("NO_FILE_CHECK")) begin
             $readmemh("src/test_data/ppu_inputs.mem", mem_inputs);
             $readmemh("src/test_data/ppu_golden.mem", mem_golden);
             $readmemh("src/test_data/ppu_config.mem", mem_config);
        end

        // Load Config
        cfg_mult  = mem_config[0][15:0];
        cfg_shift = mem_config[1][4:0];
        cfg_zp    = mem_config[2][7:0];
        cfg_bias  = mem_config[3][31:0]; // NEW
        
        $display("[TB] Config: Mult=%d, Shift=%d, ZP=%d, Bias=%d", 
                 cfg_mult, cfg_shift, cfg_zp, $signed(cfg_bias));

        clk = 0; rst_n = 0; i_valid = 0; i_data_vec = 0;
        #20 rst_n = 1; #20;

        for (i = 0; i < NUM_TESTS; i = i + 1) begin
            @(posedge clk);
            i_valid <= 1;
            i_data_vec <= mem_inputs[i];

            @(posedge clk);
            i_valid <= 0;
            #1; // Wait for output reg

            if (o_valid !== 1) begin
                $display("[FAIL] Vector %0d: o_valid missing", i);
                err_count = err_count + 1;
            end else if (o_data_vec !== mem_golden[i]) begin
                $display("[FAIL] Vector %0d Mismatch!", i);
                // Print detail for Lane 0
                $display("       Lane 0: Input=%d, Bias=%d, Exp=%d, Got=%d", 
                         $signed(mem_inputs[i][31:0]), $signed(cfg_bias),
                         $signed(mem_golden[i][7:0]), $signed(o_data_vec[7:0]));
                err_count = err_count + 1;
            end else begin
                $display("[PASS] Vector %0d: All lanes match!", i);
                $display("       Lane 0: Input=%d, Bias=%d, Exp=%d, Got=%d", 
                         $signed(mem_inputs[i][31:0]), $signed(cfg_bias),
                         $signed(mem_golden[i][7:0]), $signed(o_data_vec[7:0]));
            end
        end

        #20;
        if (err_count == 0) $display("\n=== SUCCESS: All vectors with Bias passed! ===\n");
        else $display("\n=== FAILURE: Found %0d Errors ===\n", err_count);
        $finish;
    end
endmodule

ppu_verify.vcd
$date
	Fri Jan 16 14:20:50 2026
$end
$version
	Icarus Verilog
$end
$timescale
	1ps
$end
$scope module ppu_tb $end
$var wire 1 ! o_valid $end
$var wire 128 " o_data_vec [127:0] $end
$var parameter 32 # NUM_TESTS $end
$var reg 32 $ cfg_bias [31:0] $end
$var reg 16 % cfg_mult [15:0] $end
$var reg 5 & cfg_shift [4:0] $end
$var reg 8 ' cfg_zp [7:0] $end
$var reg 1 ( clk $end
$var reg 512 ) i_data_vec [511:0] $end
$var reg 1 * i_valid $end
$var reg 1 + rst_n $end
$var integer 32 , err_count [31:0] $end
$var integer 32 - i [31:0] $end
$scope function get_byte $end
$var reg 128 . vec [127:0] $end
$var integer 32 / idx [31:0] $end
$upscope $end
$scope module dut $end
$var wire 32 0 cfg_bias [31:0] $end
$var wire 16 1 cfg_mult [15:0] $end
$var wire 5 2 cfg_shift [4:0] $end
$var wire 8 3 cfg_zp [7:0] $end
$var wire 1 ( clk $end
$var wire 512 4 i_data_vec [511:0] $end
$var wire 1 * i_valid $end
$var wire 1 + rst_n $end
$var wire 128 5 o_data_vec [127:0] $end
$var reg 1 ! o_valid $end
$scope begin PPU_LANE[0] $end
$var wire 32 6 in_val [31:0] $end
$var wire 48 7 with_zp [47:0] $end
$var wire 32 8 val_biased [31:0] $end
$var wire 48 9 shifted [47:0] $end
$var wire 48 : product [47:0] $end
$var wire 8 ; clamped_val [7:0] $end
$var parameter 2 < i $end
$var reg 8 = out_reg [7:0] $end
$upscope $end
$scope begin PPU_LANE[1] $end
$var wire 32 > in_val [31:0] $end
$var wire 48 ? with_zp [47:0] $end
$var wire 32 @ val_biased [31:0] $end
$var wire 48 A shifted [47:0] $end
$var wire 48 B product [47:0] $end
$var wire 8 C clamped_val [7:0] $end
$var parameter 2 D i $end
$var reg 8 E out_reg [7:0] $end
$upscope $end
$scope begin PPU_LANE[2] $end
$var wire 32 F in_val [31:0] $end
$var wire 48 G with_zp [47:0] $end
$var wire 32 H val_biased [31:0] $end
$var wire 48 I shifted [47:0] $end
$var wire 48 J product [47:0] $end
$var wire 8 K clamped_val [7:0] $end
$var parameter 3 L i $end
$var reg 8 M out_reg [7:0] $end
$upscope $end
$scope begin PPU_LANE[3] $end
$var wire 32 N in_val [31:0] $end
$var wire 48 O with_zp [47:0] $end
$var wire 32 P val_biased [31:0] $end
$var wire 48 Q shifted [47:0] $end
$var wire 48 R product [47:0] $end
$var wire 8 S clamped_val [7:0] $end
$var parameter 3 T i $end
$var reg 8 U out_reg [7:0] $end
$upscope $end
$scope begin PPU_LANE[4] $end
$var wire 32 V in_val [31:0] $end
$var wire 48 W with_zp [47:0] $end
$var wire 32 X val_biased [31:0] $end
$var wire 48 Y shifted [47:0] $end
$var wire 48 Z product [47:0] $end
$var wire 8 [ clamped_val [7:0] $end
$var parameter 4 \ i $end
$var reg 8 ] out_reg [7:0] $end
$upscope $end
$scope begin PPU_LANE[5] $end
$var wire 32 ^ in_val [31:0] $end
$var wire 48 _ with_zp [47:0] $end
$var wire 32 ` val_biased [31:0] $end
$var wire 48 a shifted [47:0] $end
$var wire 48 b product [47:0] $end
$var wire 8 c clamped_val [7:0] $end
$var parameter 4 d i $end
$var reg 8 e out_reg [7:0] $end
$upscope $end
$scope begin PPU_LANE[6] $end
$var wire 32 f in_val [31:0] $end
$var wire 48 g with_zp [47:0] $end
$var wire 32 h val_biased [31:0] $end
$var wire 48 i shifted [47:0] $end
$var wire 48 j product [47:0] $end
$var wire 8 k clamped_val [7:0] $end
$var parameter 4 l i $end
$var reg 8 m out_reg [7:0] $end
$upscope $end
$scope begin PPU_LANE[7] $end
$var wire 32 n in_val [31:0] $end
$var wire 48 o with_zp [47:0] $end
$var wire 32 p val_biased [31:0] $end
$var wire 48 q shifted [47:0] $end
$var wire 48 r product [47:0] $end
$var wire 8 s clamped_val [7:0] $end
$var parameter 4 t i $end
$var reg 8 u out_reg [7:0] $end
$upscope $end
$scope begin PPU_LANE[8] $end
$var wire 32 v in_val [31:0] $end
$var wire 48 w with_zp [47:0] $end
$var wire 32 x val_biased [31:0] $end
$var wire 48 y shifted [47:0] $end
$var wire 48 z product [47:0] $end
$var wire 8 { clamped_val [7:0] $end
$var parameter 5 | i $end
$var reg 8 } out_reg [7:0] $end
$upscope $end
$scope begin PPU_LANE[9] $end
$var wire 32 ~ in_val [31:0] $end
$var wire 48 !" with_zp [47:0] $end
$var wire 32 "" val_biased [31:0] $end
$var wire 48 #" shifted [47:0] $end
$var wire 48 $" product [47:0] $end
$var wire 8 %" clamped_val [7:0] $end
$var parameter 5 &" i $end
$var reg 8 '" out_reg [7:0] $end
$upscope $end
$scope begin PPU_LANE[10] $end
$var wire 32 (" in_val [31:0] $end
$var wire 48 )" with_zp [47:0] $end
$var wire 32 *" val_biased [31:0] $end
$var wire 48 +" shifted [47:0] $end
$var wire 48 ," product [47:0] $end
$var wire 8 -" clamped_val [7:0] $end
$var parameter 5 ." i $end
$var reg 8 /" out_reg [7:0] $end
$upscope $end
$scope begin PPU_LANE[11] $end
$var wire 32 0" in_val [31:0] $end
$var wire 48 1" with_zp [47:0] $end
$var wire 32 2" val_biased [31:0] $end
$var wire 48 3" shifted [47:0] $end
$var wire 48 4" product [47:0] $end
$var wire 8 5" clamped_val [7:0] $end
$var parameter 5 6" i $end
$var reg 8 7" out_reg [7:0] $end
$upscope $end
$scope begin PPU_LANE[12] $end
$var wire 32 8" in_val [31:0] $end
$var wire 48 9" with_zp [47:0] $end
$var wire 32 :" val_biased [31:0] $end
$var wire 48 ;" shifted [47:0] $end
$var wire 48 <" product [47:0] $end
$var wire 8 =" clamped_val [7:0] $end
$var parameter 5 >" i $end
$var reg 8 ?" out_reg [7:0] $end
$upscope $end
$scope begin PPU_LANE[13] $end
$var wire 32 @" in_val [31:0] $end
$var wire 48 A" with_zp [47:0] $end
$var wire 32 B" val_biased [31:0] $end
$var wire 48 C" shifted [47:0] $end
$var wire 48 D" product [47:0] $end
$var wire 8 E" clamped_val [7:0] $end
$var parameter 5 F" i $end
$var reg 8 G" out_reg [7:0] $end
$upscope $end
$scope begin PPU_LANE[14] $end
$var wire 32 H" in_val [31:0] $end
$var wire 48 I" with_zp [47:0] $end
$var wire 32 J" val_biased [31:0] $end
$var wire 48 K" shifted [47:0] $end
$var wire 48 L" product [47:0] $end
$var wire 8 M" clamped_val [7:0] $end
$var parameter 5 N" i $end
$var reg 8 O" out_reg [7:0] $end
$upscope $end
$scope begin PPU_LANE[15] $end
$var wire 32 P" in_val [31:0] $end
$var wire 48 Q" with_zp [47:0] $end
$var wire 32 R" val_biased [31:0] $end
$var wire 48 S" shifted [47:0] $end
$var wire 48 T" product [47:0] $end
$var wire 8 U" clamped_val [7:0] $end
$var parameter 5 V" i $end
$var reg 8 W" out_reg [7:0] $end
$upscope $end
$upscope $end
$upscope $end
$enddefinitions $end
$comment Show the parameter values. $end
$dumpall
b1111 V"
b1110 N"
b1101 F"
b1100 >"
b1011 6"
b1010 ."
b1001 &"
b1000 |
b111 t
b110 l
b101 d
b100 \
b11 T
b10 L
b1 D
b0 <
b1100100 #
$end
#0
$dumpvars
b0 W"
b111100 U"
b11001000000000 T"
b110010 S"
b110010 R"
b111100 Q"
b0 P"
b0 O"
b111100 M"
b11001000000000 L"
b110010 K"
b110010 J"
b111100 I"
b0 H"
b0 G"
b111100 E"
b11001000000000 D"
b110010 C"
b110010 B"
b111100 A"
b0 @"
b0 ?"
b111100 ="
b11001000000000 <"
b110010 ;"
b110010 :"
b111100 9"
b0 8"
b0 7"
b111100 5"
b11001000000000 4"
b110010 3"
b110010 2"
b111100 1"
b0 0"
b0 /"
b111100 -"
b11001000000000 ,"
b110010 +"
b110010 *"
b111100 )"
b0 ("
b0 '"
b111100 %"
b11001000000000 $"
b110010 #"
b110010 ""
b111100 !"
b0 ~
b0 }
b111100 {
b11001000000000 z
b110010 y
b110010 x
b111100 w
b0 v
b0 u
b111100 s
b11001000000000 r
b110010 q
b110010 p
b111100 o
b0 n
b0 m
b111100 k
b11001000000000 j
b110010 i
b110010 h
b111100 g
b0 f
b0 e
b111100 c
b11001000000000 b
b110010 a
b110010 `
b111100 _
b0 ^
b0 ]
b111100 [
b11001000000000 Z
b110010 Y
b110010 X
b111100 W
b0 V
b0 U
b111100 S
b11001000000000 R
b110010 Q
b110010 P
b111100 O
b0 N
b0 M
b111100 K
b11001000000000 J
b110010 I
b110010 H
b111100 G
b0 F
b0 E
b111100 C
b11001000000000 B
b110010 A
b110010 @
b111100 ?
b0 >
b0 =
b111100 ;
b11001000000000 :
b110010 9
b110010 8
b111100 7
b0 6
b0 5
b0 4
b1010 3
b1000 2
b100000000 1
b110010 0
bx /
bx .
bx -
b0 ,
0+
0*
b0 )
0(
b1010 '
b1000 &
b100000000 %
b110010 $
b0 "
0!
$end
#5000
1(
#10000
0(
#15000
1(
#20000
0(
1+
#25000
1(
#30000
0(
#35000
1(
#40000
0(
b0 -
#45000
b11010 ;
b11001110 C
b1110100 K
b1110101 c
b10100001 k
b10011100 s
b100 {
b101100 -"
b10011 ="
b11011000 E"
b1101111 M"
b1111111 S
b1111111 [
b1111111 %"
b1111111 5"
b1111111 U"
b11010 7
b10000 9
b1000000000000 :
b10000 8
b11111111111111111111111111011110 6
b111111111111111111111111111111111111111111001110 ?
b111111111111111111111111111111111111111111000100 A
b111111111111111111111111111111111100010000000000 B
b11111111111111111111111111000100 @
b11111111111111111111111110010010 >
b1110100 G
b1101010 I
b110101000000000 J
b1101010 H
b111000 F
b10011011 O
b10010001 Q
b1001000100000000 R
b10010001 P
b1011111 N
b10011111 W
b10010101 Y
b1001010100000000 Z
b10010101 X
b1100011 V
b1110101 _
b1101011 a
b110101100000000 b
b1101011 `
b111001 ^
b111111111111111111111111111111111111111110100001 g
b111111111111111111111111111111111111111110010111 i
b111111111111111111111111111111111001011100000000 j
b11111111111111111111111110010111 h
b11111111111111111111111101100101 f
b111111111111111111111111111111111111111110011100 o
b111111111111111111111111111111111111111110010010 q
b111111111111111111111111111111111001001000000000 r
b11111111111111111111111110010010 p
b11111111111111111111111101100000 n
b100 w
b111111111111111111111111111111111111111111111010 y
b111111111111111111111111111111111111101000000000 z
b11111111111111111111111111111010 x
b11111111111111111111111111001000 v
b11111100 !"
b11110010 #"
b1111001000000000 $"
b11110010 ""
b11000000 ~
b101100 )"
b100010 +"
b10001000000000 ,"
b100010 *"
b11111111111111111111111111110000 ("
b11001111 1"
b11000101 3"
b1100010100000000 4"
b11000101 2"
b10010011 0"
b10011 9"
b1001 ;"
b100100000000 <"
b1001 :"
b11111111111111111111111111010111 8"
b111111111111111111111111111111111111111111011000 A"
b111111111111111111111111111111111111111111001110 C"
b111111111111111111111111111111111100111000000000 D"
b11111111111111111111111111001110 B"
b11111111111111111111111110011100 @"
b1101111 I"
b1100101 K"
b110010100000000 L"
b1100101 J"
b110011 H"
b11001010 Q"
b11000000 S"
b1100000000000000 T"
b11000000 R"
b10001110 P"
b10001110000000000000000000000000001100111111111111111111111111111001110011111111111111111111111111010111000000000000000000000000100100111111111111111111111111111111000000000000000000000000000011000000111111111111111111111111110010001111111111111111111111110110000011111111111111111111111101100101000000000000000000000000001110010000000000000000000000000110001100000000000000000000000001011111000000000000000000000000001110001111111111111111111111111001001011111111111111111111111111011110 )
b10001110000000000000000000000000001100111111111111111111111111111001110011111111111111111111111111010111000000000000000000000000100100111111111111111111111111111111000000000000000000000000000011000000111111111111111111111111110010001111111111111111111111110110000011111111111111111111111101100101000000000000000000000000001110010000000000000000000000000110001100000000000000000000000001011111000000000000000000000000001110001111111111111111111111111001001011111111111111111111111111011110 4
1*
1(
#50000
0(
#55000
b11010 =
b11001110 E
b1110100 M
b1111111 U
b1111111 ]
b1110101 e
b10100001 m
b10011100 u
b100 }
b1111111 '"
b101100 /"
b1111111 7"
b10011 ?"
b11011000 G"
b1101111 O"
b1111111011011111101100000010011011111110010110001111111000001001001110010100001011101010111111101111111011101001100111000011010 "
b1111111011011111101100000010011011111110010110001111111000001001001110010100001011101010111111101111111011101001100111000011010 5
b1111111 W"
1!
0*
1(
#56000
b1 -
#60000
0(
#65000
b10110101 C
b1011100 k
b10101100 s
b1001011 {
b101110 M"
b1111111 ;
b1111111 K
b10010000 [
b1111111 c
b10000000 %"
b1111111 -"
b110001 5"
b1111111 ="
b1111111 E"
b101011 U"
b10101011 7
b10100001 9
b1010000100000000 :
b10100001 8
b1101111 6
b111111111111111111111111111111111111111110110101 ?
b111111111111111111111111111111111111111110101011 A
b111111111111111111111111111111111010101100000000 B
b11111111111111111111111110101011 @
b11111111111111111111111101111001 >
b10100100 G
b10011010 I
b1001101000000000 J
b10011010 H
b1101000 F
b10001110 O
b10000100 Q
b1000010000000000 R
b10000100 P
b1010010 N
b111111111111111111111111111111111111111110010000 W
b111111111111111111111111111111111111111110000110 Y
b111111111111111111111111111111111000011000000000 Z
b11111111111111111111111110000110 X
b11111111111111111111111101010100 V
b10110100 _
b10101010 a
b1010101000000000 b
b10101010 `
b1111000 ^
b1011100 g
b1010010 i
b101001000000000 j
b1010010 h
b100000 f
b111111111111111111111111111111111111111110101100 o
b111111111111111111111111111111111111111110100010 q
b111111111111111111111111111111111010001000000000 r
b11111111111111111111111110100010 p
b11111111111111111111111101110000 n
b1001011 w
b1000001 y
b100000100000000 z
b1000001 x
b1111 v
b111111111111111111111111111111111111111110000000 !"
b111111111111111111111111111111111111111101110110 #"
b111111111111111111111111111111110111011000000000 $"
b11111111111111111111111101110110 ""
b11111111111111111111111101000100 ~
b11000101 )"
b10111011 +"
b1011101100000000 ,"
b10111011 *"
b10001001 ("
b110001 1"
b100111 3"
b10011100000000 4"
b100111 2"
b11111111111111111111111111110101 0"
b10010111 9"
b10001101 ;"
b1000110100000000 <"
b10001101 :"
b1011011 8"
b10110101 A"
b10101011 C"
b1010101100000000 D"
b10101011 B"
b1111001 @"
b101110 I"
b100100 K"
b10010000000000 L"
b100100 J"
b11111111111111111111111111110010 H"
b101011 Q"
b100001 S"
b10000100000000 T"
b100001 R"
b11111111111111111111111111101111 P"
0!
b11111111111111111111111111101111111111111111111111111111111100100000000000000000000000000111100100000000000000000000000001011011111111111111111111111111111101010000000000000000000000001000100111111111111111111111111101000100000000000000000000000000000011111111111111111111111111110111000000000000000000000000000000100000000000000000000000000000011110001111111111111111111111110101010000000000000000000000000001010010000000000000000000000000011010001111111111111111111111110111100100000000000000000000000001101111 )
b11111111111111111111111111101111111111111111111111111111111100100000000000000000000000000111100100000000000000000000000001011011111111111111111111111111111101010000000000000000000000001000100111111111111111111111111101000100000000000000000000000000000011111111111111111111111111110111000000000000000000000000000000100000000000000000000000000000011110001111111111111111111111110101010000000000000000000000000001010010000000000000000000000000011010001111111111111111111111110111100100000000000000000000000001101111 4
1*
1(
#70000
0(
#75000
b1111111 =
b10110101 E
b1111111 M
b10010000 ]
b1111111 e
b1011100 m
b10101100 u
b1001011 }
b10000000 '"
b1111111 /"
b110001 7"
b1111111 ?"
b1111111 G"
b101110 O"
b101011001011100111111101111111001100010111111110000000010010111010110001011100011111111001000001111111011111111011010101111111 "
b101011001011100111111101111111001100010111111110000000010010111010110001011100011111111001000001111111011111111011010101111111 5
b101011 W"
1!
0*
1(
#76000
b10 -
#80000
0(
#85000
b110110 C
b1110111 [
b11111111 k
b101001 {
b100010 5"
b10011001 M"
b11110111 ;
b10111 K
b10000101 S
b1111111 s
b1111111 %"
b11000 ="
b1111111 U"
b111111111111111111111111111111111111111111110111 7
b111111111111111111111111111111111111111111101101 9
b111111111111111111111111111111111110110100000000 :
b11111111111111111111111111101101 8
b11111111111111111111111110111011 6
b110110 ?
b101100 A
b10110000000000 B
b101100 @
b11111111111111111111111111111010 >
b10111 G
b1101 I
b110100000000 J
b1101 H
b11111111111111111111111111011011 F
b111111111111111111111111111111111111111110000101 O
b111111111111111111111111111111111111111101111011 Q
b111111111111111111111111111111110111101100000000 R
b11111111111111111111111101111011 P
b11111111111111111111111101001001 N
b1110111 W
b1101101 Y
b110110100000000 Z
b1101101 X
b111011 V
b10010000 _
b10000110 a
b1000011000000000 b
b10000110 `
b1010100 ^
b111111111111111111111111111111111111111111111111 g
b111111111111111111111111111111111111111111110101 i
b111111111111111111111111111111111111010100000000 j
b11111111111111111111111111110101 h
b11111111111111111111111111000011 f
b10010001 o
b10000111 q
b1000011100000000 r
b10000111 p
b1010101 n
b101001 w
b11111 y
b1111100000000 z
b11111 x
b11111111111111111111111111101101 v
b11011010 !"
b11010000 #"
b1101000000000000 $"
b11010000 ""
b10011110 ~
b11100101 )"
b11011011 +"
b1101101100000000 ,"
b11011011 *"
b10101001 ("
b100010 1"
b11000 3"
b1100000000000 4"
b11000 2"
b11111111111111111111111111100110 0"
b11000 9"
b1110 ;"
b111000000000 <"
b1110 :"
b11111111111111111111111111011100 8"
b10000110 A"
b1111100 C"
b111110000000000 D"
b1111100 B"
b1001010 @"
b111111111111111111111111111111111111111110011001 I"
b111111111111111111111111111111111111111110001111 K"
b111111111111111111111111111111111000111100000000 L"
b11111111111111111111111110001111 J"
b11111111111111111111111101011101 H"
b10000110 Q"
b1111100 S"
b111110000000000 T"
b1111100 R"
b1001010 P"
0!
b1001010111111111111111111111111010111010000000000000000000000000100101011111111111111111111111111011100111111111111111111111111111001100000000000000000000000001010100100000000000000000000000010011110111111111111111111111111111011010000000000000000000000000101010111111111111111111111111111000011000000000000000000000000010101000000000000000000000000000011101111111111111111111111111101001001111111111111111111111111110110111111111111111111111111111111101011111111111111111111111110111011 )
b1001010111111111111111111111111010111010000000000000000000000000100101011111111111111111111111111011100111111111111111111111111111001100000000000000000000000001010100100000000000000000000000010011110111111111111111111111111111011010000000000000000000000000101010111111111111111111111111111000011000000000000000000000000010101000000000000000000000000000011101111111111111111111111111101001001111111111111111111111111110110111111111111111111111111111111101011111111111111111111111110111011 4
1*
1(
#90000
0(
#95000
b11110111 =
b110110 E
b10111 M
b10000101 U
b1110111 ]
b11111111 m
b1111111 u
b101001 }
b1111111 '"
b100010 7"
b11000 ?"
b10011001 O"
b1111111100110010111111100011000001000100111111101111111001010010111111111111111011111110111011110000101000101110011011011110111 "
b1111111100110010111111100011000001000100111111101111111001010010111111111111111011111110111011110000101000101110011011011110111 5
b1111111 W"
1!
0*
1(
#96000
b11 -
#100000
0(
#105000
b1011011 C
b1111101 K
b10001000 [
b10110100 k
b110010 5"
b1111111 ;
b1111111 S
b110111 c
b10110 s
b1111111 {
b11101010 %"
b10010000 -"
b1111111 ="
b1111111 M"
b1100010 U"
b10010111 7
b10001101 9
b1000110100000000 :
b10001101 8
b1011011 6
b1011011 ?
b1010001 A
b101000100000000 B
b1010001 @
b11111 >
b1111101 G
b1110011 I
b111001100000000 J
b1110011 H
b1000001 F
b11101100 O
b11100010 Q
b1110001000000000 R
b11100010 P
b10110000 N
b111111111111111111111111111111111111111110001000 W
b111111111111111111111111111111111111111101111110 Y
b111111111111111111111111111111110111111000000000 Z
b11111111111111111111111101111110 X
b11111111111111111111111101001100 V
b110111 _
b101101 a
b10110100000000 b
b101101 `
b11111111111111111111111111111011 ^
b111111111111111111111111111111111111111110110100 g
b111111111111111111111111111111111111111110101010 i
b111111111111111111111111111111111010101000000000 j
b11111111111111111111111110101010 h
b11111111111111111111111101111000 f
b10110 o
b1100 q
b110000000000 r
b1100 p
b11111111111111111111111111011010 n
b11100011 w
b11011001 y
b1101100100000000 z
b11011001 x
b10100111 v
b111111111111111111111111111111111111111111101010 !"
b111111111111111111111111111111111111111111100000 #"
b111111111111111111111111111111111110000000000000 $"
b11111111111111111111111111100000 ""
b11111111111111111111111110101110 ~
b111111111111111111111111111111111111111110010000 )"
b111111111111111111111111111111111111111110000110 +"
b111111111111111111111111111111111000011000000000 ,"
b11111111111111111111111110000110 *"
b11111111111111111111111101010100 ("
b110010 1"
b101000 3"
b10100000000000 4"
b101000 2"
b11111111111111111111111111110110 0"
b11000110 9"
b10111100 ;"
b1011110000000000 <"
b10111100 :"
b10001010 8"
b10101000 A"
b10011110 C"
b1001111000000000 D"
b10011110 B"
b1101100 @"
b11101110 I"
b11100100 K"
b1110010000000000 L"
b11100100 J"
b10110010 H"
b1100010 Q"
b1011000 S"
b101100000000000 T"
b1011000 R"
b100110 P"
0!
b100110000000000000000000000000101100100000000000000000000000000110110000000000000000000000000010001010111111111111111111111111111101101111111111111111111111110101010011111111111111111111111110101110000000000000000000000000101001111111111111111111111111111101101011111111111111111111111101111000111111111111111111111111111110111111111111111111111111110100110000000000000000000000000010110000000000000000000000000000010000010000000000000000000000000001111100000000000000000000000001011011 )
b100110000000000000000000000000101100100000000000000000000000000110110000000000000000000000000010001010111111111111111111111111111101101111111111111111111111110101010011111111111111111111111110101110000000000000000000000000101001111111111111111111111111111101101011111111111111111111111101111000111111111111111111111111111110111111111111111111111111110100110000000000000000000000000010110000000000000000000000000000010000010000000000000000000000000001111100000000000000000000000001011011 4
1*
1(
#110000
0(
#115000
b1111111 =
b1011011 E
b1111101 M
b1111111 U
b10001000 ]
b110111 e
b10110100 m
b10110 u
b1111111 }
b11101010 '"
b10010000 /"
b110010 7"
b1111111 ?"
b1111111 O"
b1100010011111110111111101111111001100101001000011101010011111110001011010110100001101111000100001111111011111010101101101111111 "
b1100010011111110111111101111111001100101001000011101010011111110001011010110100001101111000100001111111011111010101101101111111 5
b1100010 W"
1!
0*
1(
#116000
b100 -
#120000
0(
