src/params.vh
// -----------------------------------------------------------------------------
// 文件名: params.vh
// 描述: 定义加速器的全局参数
// -----------------------------------------------------------------------------

`ifndef PARAMS_VH
`define PARAMS_VH

// -----------------------------------------------------------------------------
// 阵列维度定义 (物理维度)
// -----------------------------------------------------------------------------
// 为了适应 Zynq-7020 的 DSP资源 (220个)，我们选择 12x16
// 注意：宏定义不加分号
`define ARRAY_ROW 12
`define ARRAY_COL 16

// -----------------------------------------------------------------------------
// 数据位宽定义
// -----------------------------------------------------------------------------
`define DATA_WIDTH    8
`define ACC_WIDTH     32
`define AXI_DATA_WIDTH 64

// -----------------------------------------------------------------------------
// 默认计数器阈值 (可运行时配置)
// -----------------------------------------------------------------------------
// DeiT-Tiny Hidden Dimension = 192.
// 我们假设每次计算处理一个 Tile 的 K 维度。
`define DEFAULT_K_DIM 192 

`endif

src/ppu.v
// -----------------------------------------------------------------------------
// 文件名: src/ppu.v
// 作者: Google FPGA Architect Mentor
// 描述: 量化后处理单元 (INT32 -> INT8) - Fixed Verilog Style
//       Formula: Clamp( (Input * Mult >> Shift) + ZP )
//       Latency: 1 Cycle (Registered Output)
// -----------------------------------------------------------------------------

`timescale 1ns / 1ps
`include "params.vh"

module ppu (
    input  wire                         clk,
    input  wire                         rst_n,

    // --- Data Path ---
    input  wire                         i_valid,
    input  wire [`ARRAY_COL*32-1:0]     i_data_vec, // 16 x INT32

    output reg                          o_valid,
    output wire [`ARRAY_COL*8-1:0]      o_data_vec, // 16 x INT8

    // --- Configuration (Static during compute) ---
    input  wire [15:0]                  cfg_mult,   // Fixed-point multiplier
    input  wire [4:0]                   cfg_shift,  // Right shift (0..31)
    input  wire [7:0]                   cfg_zp      // Zero Point
);

    // -------------------------------------------------------------------------
    // Parallel Quantization Lanes
    // -------------------------------------------------------------------------
    genvar i;
    generate
        for (i = 0; i < `ARRAY_COL; i = i + 1) begin : PPU_LANE
            
            // 1. Unpack Input
            wire signed [31:0] in_val;
            assign in_val = i_data_vec[(i*32) +: 32];

            // -----------------------------------------------------------------
            // 2. Combinational Logic (Arithmetic Chain)
            // -----------------------------------------------------------------
            
            // Step A: Multiply (32-bit * 16-bit = 48-bit)
            wire signed [47:0] product;
            assign product = $signed(in_val) * $signed(cfg_mult);

            // Step B: Shift
            // >>> 是算术右移，保留符号位
            wire signed [47:0] shifted;
            assign shifted = product >>> cfg_shift;

            // Step C: Add Zero Point
            // ZP 扩展为 48 位有符号数
            wire signed [47:0] with_zp;
            assign with_zp = shifted + $signed({ {40{1'b0}}, cfg_zp }); // ZP usually unsigned 0-255

            // Step D: Clamp / Saturate logic to INT8 [-128, 127]
            wire signed [7:0] clamped_val;
            assign clamped_val = (with_zp > 48'sd127)  ? 8'sd127 :
                                 (with_zp < -48'sd128) ? -8'sd128 :
                                 with_zp[7:0];

            // -----------------------------------------------------------------
            // 3. Sequential Logic (Pipeline Register)
            // -----------------------------------------------------------------
            reg signed [7:0] out_reg;
            
            always @(posedge clk or negedge rst_n) begin
                if (!rst_n) begin
                    out_reg <= 0;
                end else if (i_valid) begin
                    out_reg <= clamped_val;
                end
            end

            // 4. Pack Output
            assign o_data_vec[(i*8) +: 8] = out_reg;

        end
    endgenerate

    // -------------------------------------------------------------------------
    // Valid Signal Pipeline
    // -------------------------------------------------------------------------
    always @(posedge clk or negedge rst_n) begin
        if (!rst_n) o_valid <= 0;
        else        o_valid <= i_valid; // 1 cycle latency matches data path
    end

endmodule

src/ppu_tb.v
// -----------------------------------------------------------------------------
// 文件名: src/ppu_tb.v
// 描述: PPU 验证平台 (基于 Python 生成向量)
// -----------------------------------------------------------------------------
`timescale 1ns / 1ps
`include "params.vh"

module ppu_tb;

    // --- Params ---
    localparam NUM_TESTS = 100;

    // --- Signals ---
    reg clk, rst_n;
    reg i_valid;
    reg [`ARRAY_COL*32-1:0] i_data_vec;
    wire o_valid;
    wire [`ARRAY_COL*8-1:0] o_data_vec;

    reg [15:0] cfg_mult;
    reg [4:0]  cfg_shift;
    reg [7:0]  cfg_zp;

    // --- Memories for Test Data ---
    reg [`ARRAY_COL*32-1:0] mem_inputs [0:NUM_TESTS-1];
    reg [`ARRAY_COL*8-1:0]  mem_golden [0:NUM_TESTS-1];
    reg [31:0]              mem_config [0:2]; // Helper to read config

    // --- DUT ---
    ppu dut (
        .clk(clk), .rst_n(rst_n),
        .i_valid(i_valid), .i_data_vec(i_data_vec),
        .o_valid(o_valid), .o_data_vec(o_data_vec),
        .cfg_mult(cfg_mult), .cfg_shift(cfg_shift), .cfg_zp(cfg_zp)
    );

    always #5 clk = ~clk;

    // Helper: Extract byte for error reporting
    function signed [7:0] get_byte;
        input [`ARRAY_COL*8-1:0] vec;
        input integer idx;
        begin
            get_byte = vec[(idx*8) +: 8];
        end
    endfunction

    integer i, lane;
    integer err_count = 0;

    initial begin
        $dumpfile("ppu_verify.vcd");
        $dumpvars(0, ppu_tb);

        // 1. Load Data
        $display("[TB] Loading Test Vectors...");
        if ($test$plusargs("NO_FILE_CHECK")) begin
             // Optional: Skip file check
        end else begin
             $readmemh("src/test_data/ppu_inputs.mem", mem_inputs);
             $readmemh("src/test_data/ppu_golden.mem", mem_golden);
             $readmemh("src/test_data/ppu_config.mem", mem_config);
        end

        // 2. Load Config from file (Lines 0, 1, 2)
        // mem_config is 32-bit wide, take lower bits
        cfg_mult  = mem_config[0][15:0];
        cfg_shift = mem_config[1][4:0];
        cfg_zp    = mem_config[2][7:0];
        
        $display("[TB] Config Loaded: Mult=%d, Shift=%d, ZP=%d", cfg_mult, cfg_shift, cfg_zp);

        // 3. Init
        clk = 0; rst_n = 0; i_valid = 0; i_data_vec = 0;
        #20 rst_n = 1;
        #20;

        $display("[TB] Starting Simulation of %0d vectors...", NUM_TESTS);

        // 4. Main Loop
        for (i = 0; i < NUM_TESTS; i = i + 1) begin
            
            // A. Drive Input
            @(posedge clk);
            i_valid <= 1;
            i_data_vec <= mem_inputs[i];

            // B. Wait for Result (1 cycle latency)
            // Current Cycle: Input driven.
            // Next Cycle: Logic processed, Output register updates at posedge.
            @(posedge clk);
            i_valid <= 0; // Pulse valid for 1 cycle (or keep high for streaming)
            
            // Wait one small delta for valid output to settle (Registered Output)
            #1; 

            if (o_valid !== 1) begin
                $display("[FAIL] Vector %0d: o_valid did not assert!", i);
                err_count = err_count + 1;
            end else begin
                // C. Compare
                if (o_data_vec !== mem_golden[i]) begin
                    $display("[FAIL] Vector %0d Mismatch!", i);
                    $display("       Input Hex: %h", mem_inputs[i]);
                    $display("       Exp Hex:   %h", mem_golden[i]);
                    $display("       Got Hex:   %h", o_data_vec);
                    
                    // Detail Lane Check
                    for (lane = 0; lane < 16; lane = lane + 1) begin
                        if (get_byte(o_data_vec, lane) !== get_byte(mem_golden[i], lane)) begin
                             $display("       -> Lane %0d: Exp %d, Got %d", 
                                      lane, $signed(get_byte(mem_golden[i], lane)), $signed(get_byte(o_data_vec, lane)));
                        end
                    end
                    err_count = err_count + 1;
                end else begin
                    $display("[PASS] Vector %0d: All lanes match!", i);
                    $display("       Input Hex: %h", mem_inputs[i]);
                    $display("       Exp Hex:   %h", mem_golden[i]);
                    $display("       Got Hex:   %h", o_data_vec);
                end
            end
        end

        // 5. Final Report
        #20;
        $display("\n------------------------------------------------");
        if (err_count == 0) begin
            $display("=== SUCCESS: Passed all %0d random vectors! ===", NUM_TESTS);
        end else begin
            $display("=== FAILURE: Found %0d mismatches. ===", err_count);
        end
        $display("------------------------------------------------\n");
        $finish;
    end

endmodule

ppu_verify.vcd
$date
	Fri Jan 16 11:58:03 2026
$end
$version
	Icarus Verilog
$end
$timescale
	1ps
$end
$scope module ppu_tb $end
$var wire 1 ! o_valid $end
$var wire 128 " o_data_vec [127:0] $end
$var parameter 32 # NUM_TESTS $end
$var reg 16 $ cfg_mult [15:0] $end
$var reg 5 % cfg_shift [4:0] $end
$var reg 8 & cfg_zp [7:0] $end
$var reg 1 ' clk $end
$var reg 512 ( i_data_vec [511:0] $end
$var reg 1 ) i_valid $end
$var reg 1 * rst_n $end
$var integer 32 + err_count [31:0] $end
$var integer 32 , i [31:0] $end
$var integer 32 - lane [31:0] $end
$scope function get_byte $end
$var reg 128 . vec [127:0] $end
$var integer 32 / idx [31:0] $end
$upscope $end
$scope module dut $end
$var wire 16 0 cfg_mult [15:0] $end
$var wire 5 1 cfg_shift [4:0] $end
$var wire 8 2 cfg_zp [7:0] $end
$var wire 1 ' clk $end
$var wire 512 3 i_data_vec [511:0] $end
$var wire 1 ) i_valid $end
$var wire 1 * rst_n $end
$var wire 128 4 o_data_vec [127:0] $end
$var reg 1 ! o_valid $end
$scope begin PPU_LANE[0] $end
$var wire 32 5 in_val [31:0] $end
$var wire 48 6 with_zp [47:0] $end
$var wire 48 7 shifted [47:0] $end
$var wire 48 8 product [47:0] $end
$var wire 8 9 clamped_val [7:0] $end
$var parameter 2 : i $end
$var reg 8 ; out_reg [7:0] $end
$upscope $end
$scope begin PPU_LANE[1] $end
$var wire 32 < in_val [31:0] $end
$var wire 48 = with_zp [47:0] $end
$var wire 48 > shifted [47:0] $end
$var wire 48 ? product [47:0] $end
$var wire 8 @ clamped_val [7:0] $end
$var parameter 2 A i $end
$var reg 8 B out_reg [7:0] $end
$upscope $end
$scope begin PPU_LANE[2] $end
$var wire 32 C in_val [31:0] $end
$var wire 48 D with_zp [47:0] $end
$var wire 48 E shifted [47:0] $end
$var wire 48 F product [47:0] $end
$var wire 8 G clamped_val [7:0] $end
$var parameter 3 H i $end
$var reg 8 I out_reg [7:0] $end
$upscope $end
$scope begin PPU_LANE[3] $end
$var wire 32 J in_val [31:0] $end
$var wire 48 K with_zp [47:0] $end
$var wire 48 L shifted [47:0] $end
$var wire 48 M product [47:0] $end
$var wire 8 N clamped_val [7:0] $end
$var parameter 3 O i $end
$var reg 8 P out_reg [7:0] $end
$upscope $end
$scope begin PPU_LANE[4] $end
$var wire 32 Q in_val [31:0] $end
$var wire 48 R with_zp [47:0] $end
$var wire 48 S shifted [47:0] $end
$var wire 48 T product [47:0] $end
$var wire 8 U clamped_val [7:0] $end
$var parameter 4 V i $end
$var reg 8 W out_reg [7:0] $end
$upscope $end
$scope begin PPU_LANE[5] $end
$var wire 32 X in_val [31:0] $end
$var wire 48 Y with_zp [47:0] $end
$var wire 48 Z shifted [47:0] $end
$var wire 48 [ product [47:0] $end
$var wire 8 \ clamped_val [7:0] $end
$var parameter 4 ] i $end
$var reg 8 ^ out_reg [7:0] $end
$upscope $end
$scope begin PPU_LANE[6] $end
$var wire 32 _ in_val [31:0] $end
$var wire 48 ` with_zp [47:0] $end
$var wire 48 a shifted [47:0] $end
$var wire 48 b product [47:0] $end
$var wire 8 c clamped_val [7:0] $end
$var parameter 4 d i $end
$var reg 8 e out_reg [7:0] $end
$upscope $end
$scope begin PPU_LANE[7] $end
$var wire 32 f in_val [31:0] $end
$var wire 48 g with_zp [47:0] $end
$var wire 48 h shifted [47:0] $end
$var wire 48 i product [47:0] $end
$var wire 8 j clamped_val [7:0] $end
$var parameter 4 k i $end
$var reg 8 l out_reg [7:0] $end
$upscope $end
$scope begin PPU_LANE[8] $end
$var wire 32 m in_val [31:0] $end
$var wire 48 n with_zp [47:0] $end
$var wire 48 o shifted [47:0] $end
$var wire 48 p product [47:0] $end
$var wire 8 q clamped_val [7:0] $end
$var parameter 5 r i $end
$var reg 8 s out_reg [7:0] $end
$upscope $end
$scope begin PPU_LANE[9] $end
$var wire 32 t in_val [31:0] $end
$var wire 48 u with_zp [47:0] $end
$var wire 48 v shifted [47:0] $end
$var wire 48 w product [47:0] $end
$var wire 8 x clamped_val [7:0] $end
$var parameter 5 y i $end
$var reg 8 z out_reg [7:0] $end
$upscope $end
$scope begin PPU_LANE[10] $end
$var wire 32 { in_val [31:0] $end
$var wire 48 | with_zp [47:0] $end
$var wire 48 } shifted [47:0] $end
$var wire 48 ~ product [47:0] $end
$var wire 8 !" clamped_val [7:0] $end
$var parameter 5 "" i $end
$var reg 8 #" out_reg [7:0] $end
$upscope $end
$scope begin PPU_LANE[11] $end
$var wire 32 $" in_val [31:0] $end
$var wire 48 %" with_zp [47:0] $end
$var wire 48 &" shifted [47:0] $end
$var wire 48 '" product [47:0] $end
$var wire 8 (" clamped_val [7:0] $end
$var parameter 5 )" i $end
$var reg 8 *" out_reg [7:0] $end
$upscope $end
$scope begin PPU_LANE[12] $end
$var wire 32 +" in_val [31:0] $end
$var wire 48 ," with_zp [47:0] $end
$var wire 48 -" shifted [47:0] $end
$var wire 48 ." product [47:0] $end
$var wire 8 /" clamped_val [7:0] $end
$var parameter 5 0" i $end
$var reg 8 1" out_reg [7:0] $end
$upscope $end
$scope begin PPU_LANE[13] $end
$var wire 32 2" in_val [31:0] $end
$var wire 48 3" with_zp [47:0] $end
$var wire 48 4" shifted [47:0] $end
$var wire 48 5" product [47:0] $end
$var wire 8 6" clamped_val [7:0] $end
$var parameter 5 7" i $end
$var reg 8 8" out_reg [7:0] $end
$upscope $end
$scope begin PPU_LANE[14] $end
$var wire 32 9" in_val [31:0] $end
$var wire 48 :" with_zp [47:0] $end
$var wire 48 ;" shifted [47:0] $end
$var wire 48 <" product [47:0] $end
$var wire 8 =" clamped_val [7:0] $end
$var parameter 5 >" i $end
$var reg 8 ?" out_reg [7:0] $end
$upscope $end
$scope begin PPU_LANE[15] $end
$var wire 32 @" in_val [31:0] $end
$var wire 48 A" with_zp [47:0] $end
$var wire 48 B" shifted [47:0] $end
$var wire 48 C" product [47:0] $end
$var wire 8 D" clamped_val [7:0] $end
$var parameter 5 E" i $end
$var reg 8 F" out_reg [7:0] $end
$upscope $end
$upscope $end
$upscope $end
$enddefinitions $end
$comment Show the parameter values. $end
$dumpall
b1111 E"
b1110 >"
b1101 7"
b1100 0"
b1011 )"
b1010 ""
b1001 y
b1000 r
b111 k
b110 d
b101 ]
b100 V
b11 O
b10 H
b1 A
b0 :
b1100100 #
$end
#0
$dumpvars
b0 F"
b1010 D"
b0 C"
b0 B"
b1010 A"
b0 @"
b0 ?"
b1010 ="
b0 <"
b0 ;"
b1010 :"
b0 9"
b0 8"
b1010 6"
b0 5"
b0 4"
b1010 3"
b0 2"
b0 1"
b1010 /"
b0 ."
b0 -"
b1010 ,"
b0 +"
b0 *"
b1010 ("
b0 '"
b0 &"
b1010 %"
b0 $"
b0 #"
b1010 !"
b0 ~
b0 }
b1010 |
b0 {
b0 z
b1010 x
b0 w
b0 v
b1010 u
b0 t
b0 s
b1010 q
b0 p
b0 o
b1010 n
b0 m
b0 l
b1010 j
b0 i
b0 h
b1010 g
b0 f
b0 e
b1010 c
b0 b
b0 a
b1010 `
b0 _
b0 ^
b1010 \
b0 [
b0 Z
b1010 Y
b0 X
b0 W
b1010 U
b0 T
b0 S
b1010 R
b0 Q
b0 P
b1010 N
b0 M
b0 L
b1010 K
b0 J
b0 I
b1010 G
b0 F
b0 E
b1010 D
b0 C
b0 B
b1010 @
b0 ?
b0 >
b1010 =
b0 <
b0 ;
b1010 9
b0 8
b0 7
b1010 6
b0 5
b0 4
b0 3
b1010 2
b1000 1
b100000000 0
bx /
bx .
bx -
bx ,
b0 +
0*
0)
b0 (
0'
b1010 &
b1000 %
b100000000 $
b0 "
0!
$end
#5000
1'
#10000
0'
#15000
1'
#20000
0'
1*
#25000
1'
#30000
0'
#35000
1'
#40000
0'
b0 ,
#45000
b11001001 9
b11011001 @
b1001101 N
b100101 q
b1110111 x
b101100 ="
b10011101 D"
b10000000 G
b10000000 U
b10000000 c
b10000000 j
b10000000 ("
b10000000 /"
b1111111 \
b1111111 !"
b1111111 6"
b111111111111111111111111111111111111111111001001 6
b111111111111111111111111111111111111111110111111 7
b111111111111111111111111111111111011111100000000 8
b11111111111111111111111110111111 5
b111111111111111111111111111111111111111111011001 =
b111111111111111111111111111111111111111111001111 >
b111111111111111111111111111111111100111100000000 ?
b11111111111111111111111111001111 <
b111111111111111111111111111111111111111100000000 D
b111111111111111111111111111111111111111011110110 E
b111111111111111111111111111111101111011000000000 F
b11111111111111111111111011110110 C
b1001101 K
b1000011 L
b100001100000000 M
b1000011 J
b111111111111111111111111111111111111111000110010 R
b111111111111111111111111111111111111111000101000 S
b111111111111111111111111111111100010100000000000 T
b11111111111111111111111000101000 Q
b10101011 Y
b10100001 Z
b1010000100000000 [
b10100001 X
b111111111111111111111111111111111111111000111100 `
b111111111111111111111111111111111111111000110010 a
b111111111111111111111111111111100011001000000000 b
b11111111111111111111111000110010 _
b111111111111111111111111111111111111111101111011 g
b111111111111111111111111111111111111111101110001 h
b111111111111111111111111111111110111000100000000 i
b11111111111111111111111101110001 f
b100101 n
b11011 o
b1101100000000 p
b11011 m
b1110111 u
b1101101 v
b110110100000000 w
b1101101 t
b101001010 |
b101000000 }
b10100000000000000 ~
b101000000 {
b111111111111111111111111111111111111111010001100 %"
b111111111111111111111111111111111111111010000010 &"
b111111111111111111111111111111101000001000000000 '"
b11111111111111111111111010000010 $"
b111111111111111111111111111111111111111001110111 ,"
b111111111111111111111111111111111111111001101101 -"
b111111111111111111111111111111100110110100000000 ."
b11111111111111111111111001101101 +"
b110011010 3"
b110010000 4"
b11001000000000000 5"
b110010000 2"
b101100 :"
b100010 ;"
b10001000000000 <"
b100010 9"
b111111111111111111111111111111111111111110011101 A"
b111111111111111111111111111111111111111110010011 B"
b111111111111111111111111111111111001001100000000 C"
b11111111111111111111111110010011 @"
b11111111111111111111111110010011000000000000000000000000001000100000000000000000000000011001000011111111111111111111111001101101111111111111111111111110100000100000000000000000000000010100000000000000000000000000000001101101000000000000000000000000000110111111111111111111111111110111000111111111111111111111111000110010000000000000000000000000101000011111111111111111111111100010100000000000000000000000000001000011111111111111111111111110111101101111111111111111111111111100111111111111111111111111111110111111 (
b11111111111111111111111110010011000000000000000000000000001000100000000000000000000000011001000011111111111111111111111001101101111111111111111111111110100000100000000000000000000000010100000000000000000000000000000001101101000000000000000000000000000110111111111111111111111111110111000111111111111111111111111000110010000000000000000000000000101000011111111111111111111111100010100000000000000000000000000001000011111111111111111111111110111101101111111111111111111111111100111111111111111111111111111110111111 3
1)
1'
#50000
0'
#55000
b11001001 ;
b11011001 B
b10000000 I
b1001101 P
b10000000 W
b1111111 ^
b10000000 e
b10000000 l
b100101 s
b1110111 z
b1111111 #"
b10000000 *"
b10000000 1"
b1111111 8"
b101100 ?"
b10011101001011000111111110000000100000000111111101110111001001011000000010000000011111111000000001001101100000001101100111001001 "
b10011101001011000111111110000000100000000111111101110111001001011000000010000000011111111000000001001101100000001101100111001001 4
b10011101 F"
1!
0)
1'
#56000
b1 ,
#60000
0'
#65000
b11011101 9
b111100 q
b1010000 ="
b10000000 @
b10011101 c
b1111111 G
b1111111 N
b1111111 x
b10001110 !"
b1111111 D"
b111111111111111111111111111111111111111111011101 6
b111111111111111111111111111111111111111111010011 7
b111111111111111111111111111111111101001100000000 8
b11111111111111111111111111010011 5
b111111111111111111111111111111111111111101000111 =
b111111111111111111111111111111111111111100111101 >
b111111111111111111111111111111110011110100000000 ?
b11111111111111111111111100111101 <
b110000111 D
b101111101 E
b10111110100000000 F
b101111101 C
b10001101 K
b10000011 L
b1000001100000000 M
b10000011 J
b111111111111111111111111111111111111111100011001 R
b111111111111111111111111111111111111111100001111 S
b111111111111111111111111111111110000111100000000 T
b11111111111111111111111100001111 Q
b11110010 Y
b11101000 Z
b1110100000000000 [
b11101000 X
b111111111111111111111111111111111111111110011101 `
b111111111111111111111111111111111111111110010011 a
b111111111111111111111111111111111001001100000000 b
b11111111111111111111111110010011 _
b111111111111111111111111111111111111111000011010 g
b111111111111111111111111111111111111111000010000 h
b111111111111111111111111111111100001000000000000 i
b11111111111111111111111000010000 f
b111100 n
b110010 o
b11001000000000 p
b110010 m
b10001010 u
b10000000 v
b1000000000000000 w
b10000000 t
b111111111111111111111111111111111111111110001110 |
b111111111111111111111111111111111111111110000100 }
b111111111111111111111111111111111000010000000000 ~
b11111111111111111111111110000100 {
b111111111111111111111111111111111111111100110100 %"
b111111111111111111111111111111111111111100101010 &"
b111111111111111111111111111111110010101000000000 '"
b11111111111111111111111100101010 $"
b111111111111111111111111111111111111111101100110 ,"
b111111111111111111111111111111111111111101011100 -"
b111111111111111111111111111111110101110000000000 ."
b11111111111111111111111101011100 +"
b100001110 3"
b100000100 4"
b10000010000000000 5"
b100000100 2"
b1010000 :"
b1000110 ;"
b100011000000000 <"
b1000110 9"
b11000010 A"
b10111000 B"
b1011100000000000 C"
b10111000 @"
0!
b10111000000000000000000000000000010001100000000000000000000000010000010011111111111111111111111101011100111111111111111111111111001010101111111111111111111111111000010000000000000000000000000010000000000000000000000000000000001100101111111111111111111111100001000011111111111111111111111110010011000000000000000000000000111010001111111111111111111111110000111100000000000000000000000010000011000000000000000000000001011111011111111111111111111111110011110111111111111111111111111111010011 (
b10111000000000000000000000000000010001100000000000000000000000010000010011111111111111111111111101011100111111111111111111111111001010101111111111111111111111111000010000000000000000000000000010000000000000000000000000000000001100101111111111111111111111100001000011111111111111111111111110010011000000000000000000000000111010001111111111111111111111110000111100000000000000000000000010000011000000000000000000000001011111011111111111111111111111110011110111111111111111111111111111010011 3
1)
1'
#70000
0'
#75000
b11011101 ;
b10000000 B
b1111111 I
b1111111 P
b10011101 e
b111100 s
b1111111 z
b10001110 #"
b1010000 ?"
b1111111010100000111111110000000100000001000111001111111001111001000000010011101011111111000000001111111011111111000000011011101 "
b1111111010100000111111110000000100000001000111001111111001111001000000010011101011111111000000001111111011111111000000011011101 4
b1111111 F"
1!
0)
1'
#76000
b10 ,
#80000
0'
#85000
b1010101 9
b11111011 ="
b10000000 c
b10000000 q
b11001011 /"
b100000 G
b10110 N
b1111111 U
b10000000 \
b1011101 x
b1111111 !"
b10000000 6"
b1010101 6
b1001011 7
b100101100000000 8
b1001011 5
b111111111111111111111111111111111111111010111001 =
b111111111111111111111111111111111111111010101111 >
b111111111111111111111111111111101010111100000000 ?
b11111111111111111111111010101111 <
b100000 D
b10110 E
b1011000000000 F
b10110 C
b10110 K
b1100 L
b110000000000 M
b1100 J
b11101111 R
b11100101 S
b1110010100000000 T
b11100101 Q
b111111111111111111111111111111111111111010111111 Y
b111111111111111111111111111111111111111010110101 Z
b111111111111111111111111111111101011010100000000 [
b11111111111111111111111010110101 X
b111111111111111111111111111111111111111100001001 `
b111111111111111111111111111111111111111011111111 a
b111111111111111111111111111111101111111100000000 b
b11111111111111111111111011111111 _
b111111111111111111111111111111111111111001000000 g
b111111111111111111111111111111111111111000110110 h
b111111111111111111111111111111100011011000000000 i
b11111111111111111111111000110110 f
b111111111111111111111111111111111111111001100111 n
b111111111111111111111111111111111111111001011101 o
b111111111111111111111111111111100101110100000000 p
b11111111111111111111111001011101 m
b1011101 u
b1010011 v
b101001100000000 w
b1010011 t
b101101011 |
b101100001 }
b10110000100000000 ~
b101100001 {
b111111111111111111111111111111111111111011111100 %"
b111111111111111111111111111111111111111011110010 &"
b111111111111111111111111111111101111001000000000 '"
b11111111111111111111111011110010 $"
b111111111111111111111111111111111111111111001011 ,"
b111111111111111111111111111111111111111111000001 -"
b111111111111111111111111111111111100000100000000 ."
b11111111111111111111111111000001 +"
b111111111111111111111111111111111111111010101010 3"
b111111111111111111111111111111111111111010100000 4"
b111111111111111111111111111111101010000000000000 5"
b11111111111111111111111010100000 2"
b111111111111111111111111111111111111111111111011 :"
b111111111111111111111111111111111111111111110001 ;"
b111111111111111111111111111111111111000100000000 <"
b11111111111111111111111111110001 9"
b11100011 A"
b11011001 B"
b1101100100000000 C"
b11011001 @"
0!
b11011001111111111111111111111111111100011111111111111111111111101010000011111111111111111111111111000001111111111111111111111110111100100000000000000000000000010110000100000000000000000000000001010011111111111111111111111110010111011111111111111111111111100011011011111111111111111111111011111111111111111111111111111110101101010000000000000000000000001110010100000000000000000000000000001100000000000000000000000000000101101111111111111111111111101010111100000000000000000000000001001011 (
b11011001111111111111111111111111111100011111111111111111111111101010000011111111111111111111111111000001111111111111111111111110111100100000000000000000000000010110000100000000000000000000000001010011111111111111111111111110010111011111111111111111111111100011011011111111111111111111111011111111111111111111111111111110101101010000000000000000000000001110010100000000000000000000000000001100000000000000000000000000000101101111111111111111111111101010111100000000000000000000000001001011 3
1)
1'
#90000
0'
#95000
b1010101 ;
b100000 I
b10110 P
b1111111 W
b10000000 ^
b10000000 e
b10000000 s
b1011101 z
b1111111 #"
b11001011 1"
b10000000 8"
b1111111111110111000000011001011100000000111111101011101100000001000000010000000100000000111111100010110001000001000000001010101 "
b1111111111110111000000011001011100000000111111101011101100000001000000010000000100000000111111100010110001000001000000001010101 4
b11111011 ?"
1!
0)
1'
#96000
b11 ,
#100000
0'
#105000
b10000000 9
b10000000 G
b1110010 j
b11010111 ("
b10000000 ="
b1111111 @
b1111111 N
b111011 U
b1111111 c
b1111111 q
b1111111 x
b10000000 !"
b1111111 /"
b111111111111111111111111111111111111111000100011 6
b111111111111111111111111111111111111111000011001 7
b111111111111111111111111111111100001100100000000 8
b11111111111111111111111000011001 5
b101111111 =
b101110101 >
b10111010100000000 ?
b101110101 <
b111111111111111111111111111111111111111001110000 D
b111111111111111111111111111111111111111001100110 E
b111111111111111111111111111111100110011000000000 F
b11111111111111111111111001100110 C
b11101110 K
b11100100 L
b1110010000000000 M
b11100100 J
b111011 R
b110001 S
b11000100000000 T
b110001 Q
b111111111111111111111111111111111111111011110010 Y
b111111111111111111111111111111111111111011101000 Z
b111111111111111111111111111111101110100000000000 [
b11111111111111111111111011101000 X
b100001110 `
b100000100 a
b10000010000000000 b
b100000100 _
b1110010 g
b1101000 h
b110100000000000 i
b1101000 f
b100001010 n
b100000000 o
b10000000000000000 p
b100000000 m
b110111001 u
b110101111 v
b11010111100000000 w
b110101111 t
b111111111111111111111111111111111111111011100110 |
b111111111111111111111111111111111111111011011100 }
b111111111111111111111111111111101101110000000000 ~
b11111111111111111111111011011100 {
b111111111111111111111111111111111111111111010111 %"
b111111111111111111111111111111111111111111001101 &"
b111111111111111111111111111111111100110100000000 '"
b11111111111111111111111111001101 $"
b10001001 ,"
b1111111 -"
b111111100000000 ."
b1111111 +"
b111111111111111111111111111111111111111001100110 3"
b111111111111111111111111111111111111111001011100 4"
b111111111111111111111111111111100101110000000000 5"
b11111111111111111111111001011100 2"
b111111111111111111111111111111111111111010101011 :"
b111111111111111111111111111111111111111010100001 ;"
b111111111111111111111111111111101010000100000000 <"
b11111111111111111111111010100001 9"
b111100101 A"
b111011011 B"
b11101101100000000 C"
b111011011 @"
0!
b111011011111111111111111111111110101000011111111111111111111111100101110000000000000000000000000001111111111111111111111111111111110011011111111111111111111111101101110000000000000000000000000110101111000000000000000000000001000000000000000000000000000000000110100000000000000000000000000100000100111111111111111111111110111010000000000000000000000000000011000100000000000000000000000011100100111111111111111111111110011001100000000000000000000000010111010111111111111111111111111000011001 (
b111011011111111111111111111111110101000011111111111111111111111100101110000000000000000000000000001111111111111111111111111111111110011011111111111111111111111101101110000000000000000000000000110101111000000000000000000000001000000000000000000000000000000000110100000000000000000000000000100000100111111111111111111111110111010000000000000000000000000000011000100000000000000000000000011100100111111111111111111111110011001100000000000000000000000010111010111111111111111111111111000011001 3
1)
1'
#110000
0'
#115000
b10000000 ;
b1111111 B
b10000000 I
b1111111 P
b111011 W
b1111111 e
b1110010 l
b1111111 s
b1111111 z
b10000000 #"
b11010111 *"
b1111111 1"
b1111111100000001000000001111111110101111000000001111111011111110111001001111111100000000011101101111111100000000111111110000000 "
b1111111100000001000000001111111110101111000000001111111011111110111001001111111100000000011101101111111100000000111111110000000 4
b10000000 ?"
1!
0)
1'
#116000
b100 ,
#120000
0'
