src/params.vh
// -----------------------------------------------------------------------------
// 文件名: params.vh
// 描述: 定义加速器的全局参数
// -----------------------------------------------------------------------------

`ifndef PARAMS_VH
`define PARAMS_VH

// -----------------------------------------------------------------------------
// 阵列维度定义 (物理维度)
// -----------------------------------------------------------------------------
// 为了适应 Zynq-7020 的 DSP资源 (220个)，我们选择 12x16
// 注意：宏定义不加分号
`define ARRAY_ROW 12
`define ARRAY_COL 16

// -----------------------------------------------------------------------------
// 数据位宽定义
// -----------------------------------------------------------------------------
`define DATA_WIDTH    8
`define ACC_WIDTH     32
`define AXI_DATA_WIDTH 64

// -----------------------------------------------------------------------------
// 默认计数器阈值 (可运行时配置)
// -----------------------------------------------------------------------------
// DeiT-Tiny Hidden Dimension = 192.
// 我们假设每次计算处理一个 Tile 的 K 维度。
`define DEFAULT_K_DIM 192 

`endif

src/weight_buffer_ctrl.v
// -----------------------------------------------------------------------------
// 文件名: src/weight_buffer_ctrl.v
// 作者: Google FPGA Architect Mentor
// 描述: 权重缓冲控制器 (Gearbox + Ping-Pong LUTRAM)
//       - Input: 64-bit Stream
//       - Output: 128-bit Vector (16 cols x 8 bits)
// -----------------------------------------------------------------------------

`timescale 1ns / 1ps
`include "params.vh"

module weight_buffer_ctrl (
    input  wire                         clk,
    input  wire                         rst_n,

    // --- AXI-Stream Slave (From DMA) ---
    input  wire [63:0]                  s_axis_tdata,
    input  wire                         s_axis_tvalid,
    output wire                         s_axis_tready,

    // --- Core Interface (To Systolic Array) ---
    // Core 的 ctrl_weight_load_en 连接到这里的 i_weight_load_en
    input  wire                         i_weight_load_en,
    output wire [`ARRAY_COL*8-1:0]      o_weight_vec,

    // --- Control ---
    input  wire                         i_bank_swap
);

    // -------------------------------------------------------------------------
    // 1. Constants & Parameters
    // -------------------------------------------------------------------------
    // 12 Rows per tile. Use 16 depth (4 bits) for alignment power of 2
    localparam DEPTH_LOG2 = 4; 
    
    // Output Width: 16 cols * 8 bit = 128 bit
    localparam OUT_WIDTH = `ARRAY_COL * 8;

    assign s_axis_tready = 1'b1; // Always ready

    // -------------------------------------------------------------------------
    // 2. Ping-Pong State
    // -------------------------------------------------------------------------
    reg bank_sel;
    always @(posedge clk or negedge rst_n) begin
        if (!rst_n) bank_sel <= 0;
        else if (i_bank_swap) bank_sel <= ~bank_sel;
    end

    // -------------------------------------------------------------------------
    // 3. Gearbox (64-bit -> 128-bit)
    // -------------------------------------------------------------------------
    reg        gb_cnt;         // 0: Low Word, 1: High Word
    reg [63:0] temp_low;
    
    reg [OUT_WIDTH-1:0] ram_wdata;
    reg                 ram_wen;
    
    // Write Pointer
    reg [DEPTH_LOG2-1:0] wr_ptr;
    // Pipeline Address (Critical for timing alignment, same as Input Buffer)
    reg [DEPTH_LOG2-1:0] wr_addr_pipe;

    always @(posedge clk or negedge rst_n) begin
        if (!rst_n) begin
            gb_cnt       <= 0;
            temp_low     <= 0;
            ram_wen      <= 0;
            ram_wdata    <= 0;
            wr_ptr       <= 0;
            wr_addr_pipe <= 0;
        end else begin
            ram_wen <= 0; // Default Low

            if (i_bank_swap) begin
                wr_ptr   <= 0;
                gb_cnt   <= 0;
            end 
            else if (s_axis_tvalid) begin
                if (gb_cnt == 0) begin
                    // Cycle 0: Store Low 64 bits
                    temp_low <= s_axis_tdata;
                    gb_cnt   <= 1;
                end else begin
                    // Cycle 1: Combine High + Low -> Write 128 bits
                    // Assuming Little Endian: {High, Low}
                    ram_wdata <= {s_axis_tdata, temp_low}; 
                    ram_wen   <= 1;
                    
                    // Latch current address for pipeline alignment
                    wr_addr_pipe <= wr_ptr;
                    
                    wr_ptr    <= wr_ptr + 1;
                    gb_cnt    <= 0;
                end
            end
        end
    end

    // -------------------------------------------------------------------------
    // 4. Memory (LUTRAM Inference)
    // -------------------------------------------------------------------------
    // Size: 2 Banks * 16 Depth = 32 Total Depth. Width = 128.
    // Xilinx Vivado handles this efficiently using LUTRAM (Distributed Memory)
    reg [OUT_WIDTH-1:0] ram [0:(1<<(DEPTH_LOG2+1))-1];

    // Write Port
    wire [DEPTH_LOG2:0] final_wr_addr = {bank_sel, wr_addr_pipe};

    always @(posedge clk) begin
        if (ram_wen) begin
            ram[final_wr_addr] <= ram_wdata;
        end
    end

    // Read Port
    reg [DEPTH_LOG2-1:0] rd_ptr;
    
    always @(posedge clk or negedge rst_n) begin
        if (!rst_n) begin
            rd_ptr <= 0;
        end else begin
            // Reset read pointer when not loading? 
            // The global_controller asserts load_en for exactly 12 cycles.
            // But it does not provide a reset signal.
            // We can reset rd_ptr when load_en is LOW.
            if (i_weight_load_en) 
                rd_ptr <= rd_ptr + 1;
            else
                rd_ptr <= 0;
        end
    end

    wire [DEPTH_LOG2:0] final_rd_addr = {~bank_sel, rd_ptr};
    
    // Asynchronous Read (LUTRAM characteristic) or Synchronous?
    // LUTRAMs are usually Async Read. But for timing closure, we register the output.
    // Also `deit_core` logic expects data to be valid.
    // Let's use Synchronous Read (Output Register) to match BRAM behavior of Input Buffer.
    reg [OUT_WIDTH-1:0] ram_out_reg;
    always @(posedge clk) begin
        ram_out_reg <= ram[final_rd_addr];
    end

    assign o_weight_vec = ram_out_reg;

endmodule

src/weight_buffer_ctrl_tb.v
// -----------------------------------------------------------------------------
// 文件名: src/weight_buffer_ctrl_tb.v
// 描述: 验证 Weight Buffer (Gearbox 64->128 & Ping-Pong)
// -----------------------------------------------------------------------------
`timescale 1ns / 1ps

module weight_buffer_ctrl_tb;

    reg clk, rst_n;
    reg [63:0] s_axis_tdata;
    reg s_axis_tvalid;
    wire s_axis_tready;
    
    reg i_weight_load_en;
    wire [127:0] o_weight_vec; // 16 * 8 = 128
    reg i_bank_swap;

    // DUT
    weight_buffer_ctrl dut (
        .clk(clk), .rst_n(rst_n),
        .s_axis_tdata(s_axis_tdata), .s_axis_tvalid(s_axis_tvalid), .s_axis_tready(s_axis_tready),
        .i_weight_load_en(i_weight_load_en), .o_weight_vec(o_weight_vec),
        .i_bank_swap(i_bank_swap)
    );

    always #5 clk = ~clk;

    task send_word;
        input [63:0] data;
        begin
            s_axis_tdata <= data;
            s_axis_tvalid <= 1;
            @(posedge clk);
            s_axis_tvalid <= 0;
        end
    endtask

    integer err_cnt = 0;

    initial begin
        $dumpfile("weight_verify.vcd");
        $dumpvars(0, weight_buffer_ctrl_tb);

        clk = 0; rst_n = 0;
        s_axis_tdata = 0; s_axis_tvalid = 0;
        i_weight_load_en = 0; i_bank_swap = 0;

        #20 rst_n = 1;
        #20;

        $display("=== START WEIGHT BUFFER VERIFICATION ===");

        // ---------------------------------------------------------
        // CP1: Write to Bank 0 (Gearbox Test)
        // ---------------------------------------------------------
        // Write Row 0 (128 bits): {High, Low}
        // Low:  64'h11111111_00000000
        // High: 64'h33333333_22222222
        // Result: 128'h33333333_22222222_11111111_00000000
        
        $display("[TB] Writing Row 0 to Bank 0...");
        send_word(64'h11111111_00000000); // Low
        send_word(64'h33333333_22222222); // High (Triggers Write)
        
        // Write Row 1
        // Low:  64'h55555555_44444444
        // High: 64'h77777777_66666666
        $display("[TB] Writing Row 1 to Bank 0...");
        send_word(64'h55555555_44444444); 
        send_word(64'h77777777_66666666); 

        #20;

        // ---------------------------------------------------------
        // CP2: Bank Swap & Read
        // ---------------------------------------------------------
        $display("[TB] Swapping Banks...");
        @(posedge clk); i_bank_swap = 1;
        @(posedge clk); i_bank_swap = 0;

        $display("[TB] Reading from Bank 0...");
        // Enable Read (Simulate Controller)
        i_weight_load_en = 1;
        
        // Latency 1 (Address) -> Latency 2 (Data Out)
        @(posedge clk); 
        @(posedge clk);
        
        // Check Row 0
        if (o_weight_vec === 128'h33333333_22222222_11111111_00000000)
            $display("[PASS] CP2a: Row 0 Correct.");
        else begin
            $display("[FAIL] CP2a: Row 0 Mismatch. Got %h", o_weight_vec);
            err_cnt = err_cnt + 1;
        end

        // Check Row 1 (Next cycle)
        @(posedge clk);
        if (o_weight_vec === 128'h77777777_66666666_55555555_44444444)
            $display("[PASS] CP2b: Row 1 Correct.");
        else begin
            $display("[FAIL] CP2b: Row 1 Mismatch. Got %h", o_weight_vec);
            err_cnt = err_cnt + 1;
        end

        i_weight_load_en = 0;

        // --- Final Report ---
        if (err_cnt == 0) $display("\n=== SUCCESS: All Checkpoints Passed! ===\n");
        else $display("\n=== FAILURE: Found %0d Errors ===\n", err_cnt);
        $finish;
    end

endmodule

weight_verify.vcd
$date
	Fri Jan 16 11:10:02 2026
$end
$version
	Icarus Verilog
$end
$timescale
	1ps
$end
$scope module weight_buffer_ctrl_tb $end
$var wire 1 ! s_axis_tready $end
$var wire 128 " o_weight_vec [127:0] $end
$var reg 1 # clk $end
$var reg 1 $ i_bank_swap $end
$var reg 1 % i_weight_load_en $end
$var reg 1 & rst_n $end
$var reg 64 ' s_axis_tdata [63:0] $end
$var reg 1 ( s_axis_tvalid $end
$var integer 32 ) err_cnt [31:0] $end
$scope module dut $end
$var wire 1 # clk $end
$var wire 1 $ i_bank_swap $end
$var wire 1 % i_weight_load_en $end
$var wire 128 * o_weight_vec [127:0] $end
$var wire 1 & rst_n $end
$var wire 64 + s_axis_tdata [63:0] $end
$var wire 1 ! s_axis_tready $end
$var wire 1 ( s_axis_tvalid $end
$var wire 5 , final_wr_addr [4:0] $end
$var wire 5 - final_rd_addr [4:0] $end
$var parameter 32 . DEPTH_LOG2 $end
$var parameter 64 / OUT_WIDTH $end
$var reg 1 0 bank_sel $end
$var reg 1 1 gb_cnt $end
$var reg 128 2 ram_out_reg [127:0] $end
$var reg 128 3 ram_wdata [127:0] $end
$var reg 1 4 ram_wen $end
$var reg 4 5 rd_ptr [3:0] $end
$var reg 64 6 temp_low [63:0] $end
$var reg 4 7 wr_addr_pipe [3:0] $end
$var reg 4 8 wr_ptr [3:0] $end
$upscope $end
$scope task send_word $end
$var reg 64 9 data [63:0] $end
$upscope $end
$upscope $end
$enddefinitions $end
$comment Show the parameter values. $end
$dumpall
b10000000 /
b100 .
$end
#0
$dumpvars
bx 9
b0 8
b0 7
b0 6
b0 5
04
b0 3
bx 2
01
00
b10000 -
b0 ,
b0 +
bx *
b0 )
0(
b0 '
0&
0%
0$
0#
bx "
1!
$end
#5000
1#
#10000
0#
#15000
1#
#20000
0#
1&
#25000
1#
#30000
0#
#35000
1#
#40000
1(
b1000100010001000100010001000100000000000000000000000000000000 '
b1000100010001000100010001000100000000000000000000000000000000 +
0#
b1000100010001000100010001000100000000000000000000000000000000 9
#45000
b11001100110011001100110011001100100010001000100010001000100010 '
b11001100110011001100110011001100100010001000100010001000100010 +
1(
11
b1000100010001000100010001000100000000000000000000000000000000 6
b11001100110011001100110011001100100010001000100010001000100010 9
1#
#50000
0#
#55000
b101010101010101010101010101010101000100010001000100010001000100 '
b101010101010101010101010101010101000100010001000100010001000100 +
1(
01
b1 8
14
b110011001100110011001100110011001000100010001000100010001000100001000100010001000100010001000100000000000000000000000000000000 3
b101010101010101010101010101010101000100010001000100010001000100 9
1#
#60000
0#
#65000
b111011101110111011101110111011101100110011001100110011001100110 '
b111011101110111011101110111011101100110011001100110011001100110 +
1(
11
b101010101010101010101010101010101000100010001000100010001000100 6
04
b111011101110111011101110111011101100110011001100110011001100110 9
1#
#70000
0#
#75000
0(
01
b10 8
b1 ,
b1 7
14
b1110111011101110111011101110111011001100110011001100110011001100101010101010101010101010101010101000100010001000100010001000100 3
1#
#80000
0#
#85000
04
1#
#90000
0#
#95000
1$
1#
#100000
0#
#105000
b0 -
b0 8
b10001 ,
10
1%
0$
1#
#110000
0#
#115000
b110011001100110011001100110011001000100010001000100010001000100001000100010001000100010001000100000000000000000000000000000000 "
b110011001100110011001100110011001000100010001000100010001000100001000100010001000100010001000100000000000000000000000000000000 *
b110011001100110011001100110011001000100010001000100010001000100001000100010001000100010001000100000000000000000000000000000000 2
b1 -
b1 5
1#
#120000
0#
#125000
b1110111011101110111011101110111011001100110011001100110011001100101010101010101010101010101010101000100010001000100010001000100 "
b1110111011101110111011101110111011001100110011001100110011001100101010101010101010101010101010101000100010001000100010001000100 *
b1110111011101110111011101110111011001100110011001100110011001100101010101010101010101010101010101000100010001000100010001000100 2
b10 -
b10 5
1#
#130000
0#
#135000
bx "
bx *
bx 2
b11 -
b11 5
0%
1#
