src/params.vh
// -----------------------------------------------------------------------------
// 文件名: params.vh
// 描述: 定义加速器的全局参数
// -----------------------------------------------------------------------------

`ifndef PARAMS_VH
`define PARAMS_VH

// -----------------------------------------------------------------------------
// 阵列维度定义 (物理维度)
// -----------------------------------------------------------------------------
// 为了适应 Zynq-7020 的 DSP资源 (220个)，我们选择 12x16
// 注意：宏定义不加分号
`define ARRAY_ROW 12
`define ARRAY_COL 16

// -----------------------------------------------------------------------------
// 数据位宽定义
// -----------------------------------------------------------------------------
`define DATA_WIDTH    8
`define ACC_WIDTH     32
`define AXI_DATA_WIDTH 64

// -----------------------------------------------------------------------------
// 默认计数器阈值 (可运行时配置)
// -----------------------------------------------------------------------------
// DeiT-Tiny Hidden Dimension = 192.
// 我们假设每次计算处理一个 Tile 的 K 维度。
`define DEFAULT_K_DIM 192 

`endif

src/global_controller.v
// -----------------------------------------------------------------------------
// 文件名: global_controller.v
// 作者: Google FPGA Architect Mentor
// 描述: 系统主控制器。协调权重加载、计算循环和数据输出。
// -----------------------------------------------------------------------------

`include "/Users/wangsibo/program/deit_on_fpga/src/params.vh"

module global_controller (
    input  wire                     clk,
    input  wire                     rst_n,

    // --- 来自 PS (CPU) 的 AXI-Lite 配置信号 ---
    input  wire                     ap_start,       // 启动信号 (脉冲或高电平)
    input  wire [31:0]              cfg_k_dim,      // K 维度大小 (例如 192)
    
    // --- 反馈给 PS 的状态信号 ---
    output reg                      ap_done,        // 计算完成中断
    output reg                      ap_idle,        // 空闲状态指示
    output reg  [2:0]               current_state_dbg, // 调试用：当前状态

    // --- 控制各个子模块的控制信号 ---
    output reg                      ctrl_weight_load_en, // 启用权重加载模式
    output reg                      ctrl_input_stream_en,// 启用输入数据流
    output reg                      ctrl_acc_en,         // 启用累加器
    output reg                      ctrl_drain_en        // 启用结果输出
);

    // -------------------------------------------------------------------------
    // 状态定义 (One-Hot Encoding 推荐用于高性能 FSM，但在低速控制层 Binary 亦可)
    // -------------------------------------------------------------------------
    localparam S_IDLE       = 3'd0;
    localparam S_LOAD_W     = 3'd1; // 加载权重 Tile
    localparam S_COMPUTE    = 3'd2; // 脉动阵列计算中
    localparam S_DRAIN      = 3'd3; // 排空流水线/输出结果
    localparam S_DONE       = 3'd4; // 完成握手

    reg [2:0] state, next_state;

    // -------------------------------------------------------------------------
    // 内部计数器
    // -------------------------------------------------------------------------
    reg [31:0] cnt_k;           // 追踪 K 维度的进度
    reg [31:0] cnt_load_w;      // 追踪权重加载进度
    
    // 假设权重加载需要 `ARRAY_ROW 个周期 (串行推入每一列)
    // 或者如果是并行加载，可能需要 `ARRAY_ROW 个周期将数据填满 Shift Reg
    wire [31:0] TARGET_LOAD_CYCLES = `ARRAY_ROW; 
    
    // 计算周期 = K维度 + 阵列流水线延迟 (Array Latency)
    // 脉动阵列的填充需要时间，我们这里简化模型，假设 K 周期流完输入
    wire [31:0] TARGET_COMPUTE_CYCLES = cfg_k_dim;

    // -------------------------------------------------------------------------
    // 状态机: 状态寄存器更新
    // -------------------------------------------------------------------------
    always @(posedge clk or negedge rst_n) begin
        if (!rst_n) begin
            state <= S_IDLE;
        end else begin
            state <= next_state;
        end
    end

    // -------------------------------------------------------------------------
    // 状态机: 下一状态逻辑 (Next State Logic)
    // -------------------------------------------------------------------------
    always @(*) begin
        next_state = state; // 默认保持
        case (state)
            S_IDLE: begin
                if (ap_start) 
                    next_state = S_LOAD_W;
            end

            S_LOAD_W: begin
                // 当权重加载计数器达到目标值，进入计算阶段
                if (cnt_load_w >= TARGET_LOAD_CYCLES - 1)
                    next_state = S_COMPUTE;
            end

            S_COMPUTE: begin
                // 当 K 维度所有输入向量都流过阵列后，进入排水(输出)阶段
                if (cnt_k >= TARGET_COMPUTE_CYCLES - 1)
                    next_state = S_DRAIN;
            end
            
            S_DRAIN: begin
                // 这里为了简化，假设 Drain 需要固定周期 (例如行数 + 流水线深度)
                // 暂时用固定值 10 个周期模拟 Output Drain
                // 实际项目中需要根据 Output Buffer 的 Full/Empty 信号握手
                if (cnt_k >= 10) 
                     next_state = S_DONE;
            end

            S_DONE: begin
                // 握手完成，且 Start 信号拉低后回到 IDLE (防止重复触发)
                if (!ap_start)
                    next_state = S_IDLE;
            end
            
            default: next_state = S_IDLE;
        endcase
    end

    // -------------------------------------------------------------------------
    // 输出逻辑与计数器控制
    // -------------------------------------------------------------------------
    always @(posedge clk or negedge rst_n) begin
        if (!rst_n) begin
            cnt_k           <= 0;
            cnt_load_w      <= 0;
            ap_done         <= 0;
            ap_idle         <= 1;
            ctrl_weight_load_en <= 0;
            ctrl_input_stream_en<= 0;
            ctrl_drain_en       <= 0;
        end else begin
            // 默认复位信号
            ap_done <= 0;
            
            case (state)
                S_IDLE: begin
                    ap_idle <= 1;
                    cnt_k <= 0;
                    cnt_load_w <= 0;
                    ctrl_weight_load_en <= 0;
                    ctrl_input_stream_en<= 0;
                    ctrl_drain_en <= 0;
                end

                S_LOAD_W: begin
                    ap_idle <= 0;
                    ctrl_weight_load_en <= 1;
                    cnt_load_w <= cnt_load_w + 1;
                end

                S_COMPUTE: begin
                    ctrl_weight_load_en <= 0; // 锁定权重
                    ctrl_input_stream_en<= 1; // 开始流数据
                    cnt_k <= cnt_k + 1;
                end
                
                S_DRAIN: begin
                    ctrl_input_stream_en <= 0;
                    ctrl_drain_en <= 1;
                    // 在 DRAIN 阶段复用 cnt_k 计数，实际应使用独立计数器
                    cnt_k <= cnt_k + 1; 
                end

                S_DONE: begin
                    ctrl_drain_en <= 0;
                    ap_done <= 1; // 发出完成中断
                    cnt_k <= 0;
                end
            endcase
        end
    end
    
    // 调试输出
    always @(*) current_state_dbg = state;

endmodule

src/global_controller_tb.v
// -----------------------------------------------------------------------------
// 文件名: global_controller_tb.v
// 描述: 验证 Global Controller 的状态跳转与计数器逻辑
// 运行方法 (macOS/Linux):
//    iverilog -o wave_sim params.vh global_controller.v global_controller_tb.v
//    vvp wave_sim
//    gtkwave controller_check.vcd
// -----------------------------------------------------------------------------

`timescale 1ns / 1ps
// `include "params.vh"

module global_controller_tb;

    // --- 信号定义 ---
    reg clk;
    reg rst_n;
    reg ap_start;
    reg [31:0] cfg_k_dim;

    wire ap_done;
    wire ap_idle;
    wire [2:0] current_state_dbg;
    wire ctrl_weight_load_en;
    wire ctrl_input_stream_en;
    wire ctrl_drain_en;

    // --- 实例化 DUT (Device Under Test) ---
    global_controller dut (
        .clk(clk),
        .rst_n(rst_n),
        .ap_start(ap_start),
        .cfg_k_dim(cfg_k_dim),
        .ap_done(ap_done),
        .ap_idle(ap_idle),
        .current_state_dbg(current_state_dbg),
        .ctrl_weight_load_en(ctrl_weight_load_en),
        .ctrl_input_stream_en(ctrl_input_stream_en),
        .ctrl_acc_en(), // 暂时悬空
        .ctrl_drain_en(ctrl_drain_en)
    );

    // --- 时钟生成 (100MHz, Period = 10ns) ---
    always #5 clk = ~clk;

    // --- 测试流程 ---
    initial begin
        // 1. 生成波形文件供 GTKWave 查看
        $dumpfile("controller_check.vcd");
        $dumpvars(0, global_controller_tb);

        // 2. 初始化
        clk = 0;
        rst_n = 0;
        ap_start = 0;
        cfg_k_dim = 32; // 设置一个较小的 K 用于快速仿真

        // 3. 复位释放
        #20 rst_n = 1;
        $display("Time %0t: System Reset Released", $time);

        // 4. 发送 Start 信号
        #20 ap_start = 1;
        $display("Time %0t: AP_START Triggered", $time);
        
        // 保持 Start 信号几个周期 (模拟 CPU 行为)
        #30 ap_start = 0;

        // 5. 等待完成
        wait(ap_done == 1);
        $display("Time %0t: AP_DONE Received! Checkpoint Passed.", $time);

        // 6. 再次检查是否回到 IDLE
        #20;
        if (ap_idle == 1) 
            $display("Time %0t: System correctly returned to IDLE.", $time);
        else 
            $display("Error: System stuck.");

        $finish;
    end
    
    // --- 状态监视器 ---
    always @(current_state_dbg) begin
        case(current_state_dbg)
            0: $display("Time %0t: State -> IDLE", $time);
            1: $display("Time %0t: State -> LOAD_WEIGHTS", $time);
            2: $display("Time %0t: State -> COMPUTE", $time);
            3: $display("Time %0t: State -> DRAIN", $time);
            4: $display("Time %0t: State -> DONE", $time);
        endcase
    end

endmodule

src/controller_check.vcd
$date
	Fri Jan  9 21:42:00 2026
$end
$version
	Icarus Verilog
$end
$timescale
	1ps
$end
$scope module global_controller_tb $end
$var wire 3 ! current_state_dbg [2:0] $end
$var wire 1 " ctrl_weight_load_en $end
$var wire 1 # ctrl_input_stream_en $end
$var wire 1 $ ctrl_drain_en $end
$var wire 1 % ap_idle $end
$var wire 1 & ap_done $end
$var reg 1 ' ap_start $end
$var reg 32 ( cfg_k_dim [31:0] $end
$var reg 1 ) clk $end
$var reg 1 * rst_n $end
$scope module dut $end
$var wire 32 + TARGET_COMPUTE_CYCLES [31:0] $end
$var wire 32 , TARGET_LOAD_CYCLES [31:0] $end
$var wire 1 ' ap_start $end
$var wire 32 - cfg_k_dim [31:0] $end
$var wire 1 ) clk $end
$var wire 1 * rst_n $end
$var parameter 3 . S_COMPUTE $end
$var parameter 3 / S_DONE $end
$var parameter 3 0 S_DRAIN $end
$var parameter 3 1 S_IDLE $end
$var parameter 3 2 S_LOAD_W $end
$var reg 1 & ap_done $end
$var reg 1 % ap_idle $end
$var reg 32 3 cnt_k [31:0] $end
$var reg 32 4 cnt_load_w [31:0] $end
$var reg 1 5 ctrl_acc_en $end
$var reg 1 $ ctrl_drain_en $end
$var reg 1 # ctrl_input_stream_en $end
$var reg 1 " ctrl_weight_load_en $end
$var reg 3 6 current_state_dbg [2:0] $end
$var reg 3 7 next_state [2:0] $end
$var reg 3 8 state [2:0] $end
$upscope $end
$upscope $end
$enddefinitions $end
$comment Show the parameter values. $end
$dumpall
b1 2
b0 1
b11 0
b100 /
b10 .
$end
#0
$dumpvars
b0 8
b0 7
b0 6
x5
b0 4
b0 3
b100000 -
b1100 ,
b100000 +
0*
0)
b100000 (
0'
0&
1%
0$
0#
0"
b0 !
$end
#5000
1)
#10000
0)
#15000
1)
#20000
0)
1*
#25000
1)
#30000
0)
#35000
1)
#40000
b1 7
0)
1'
#45000
b1 !
b1 6
b1 8
1)
#50000
0)
#55000
b1 4
1"
0%
1)
#60000
0)
#65000
b10 4
1)
#70000
0)
0'
#75000
b11 4
1)
#80000
0)
#85000
b100 4
1)
#90000
0)
#95000
b101 4
1)
#100000
0)
#105000
b110 4
1)
#110000
0)
#115000
b111 4
1)
#120000
0)
#125000
b1000 4
1)
#130000
0)
#135000
b1001 4
1)
#140000
0)
#145000
b1010 4
1)
#150000
0)
#155000
b10 7
b1011 4
1)
#160000
0)
#165000
b10 !
b10 6
b1100 4
b10 8
1)
#170000
0)
#175000
b1 3
1#
0"
1)
#180000
0)
#185000
b10 3
1)
#190000
0)
#195000
b11 3
1)
#200000
0)
#205000
b100 3
1)
#210000
0)
#215000
b101 3
1)
#220000
0)
#225000
b110 3
1)
#230000
0)
#235000
b111 3
1)
#240000
0)
#245000
b1000 3
1)
#250000
0)
#255000
b1001 3
1)
#260000
0)
#265000
b1010 3
1)
#270000
0)
#275000
b1011 3
1)
#280000
0)
#285000
b1100 3
1)
#290000
0)
#295000
b1101 3
1)
#300000
0)
#305000
b1110 3
1)
#310000
0)
#315000
b1111 3
1)
#320000
0)
#325000
b10000 3
1)
#330000
0)
#335000
b10001 3
1)
#340000
0)
#345000
b10010 3
1)
#350000
0)
#355000
b10011 3
1)
#360000
0)
#365000
b10100 3
1)
#370000
0)
#375000
b10101 3
1)
#380000
0)
#385000
b10110 3
1)
#390000
0)
#395000
b10111 3
1)
#400000
0)
#405000
b11000 3
1)
#410000
0)
#415000
b11001 3
1)
#420000
0)
#425000
b11010 3
1)
#430000
0)
#435000
b11011 3
1)
#440000
0)
#445000
b11100 3
1)
#450000
0)
#455000
b11101 3
1)
#460000
0)
#465000
b11110 3
1)
#470000
0)
#475000
b11 7
b11111 3
1)
#480000
0)
#485000
b11 !
b11 6
b100 7
b100000 3
b11 8
1)
#490000
0)
#495000
b100 !
b100 6
b0 7
b100 8
b100001 3
1$
0#
1)
#500000
0)
#505000
b0 !
b0 6
b0 3
1&
0$
b0 8
1)
#510000
0)
#515000
b0 4
1%
0&
1)
