src/params.vh
// -----------------------------------------------------------------------------
// 文件名: params.vh
// 描述: 定义加速器的全局参数
// -----------------------------------------------------------------------------

`ifndef PARAMS_VH
`define PARAMS_VH

// -----------------------------------------------------------------------------
// 阵列维度定义 (物理维度)
// -----------------------------------------------------------------------------
// 为了适应 Zynq-7020 的 DSP资源 (220个)，我们选择 12x16
// 注意：宏定义不加分号
`define ARRAY_ROW 12
`define ARRAY_COL 16

// -----------------------------------------------------------------------------
// 数据位宽定义
// -----------------------------------------------------------------------------
`define DATA_WIDTH    8
`define ACC_WIDTH     32
`define AXI_DATA_WIDTH 64

// -----------------------------------------------------------------------------
// 默认计数器阈值 (可运行时配置)
// -----------------------------------------------------------------------------
// DeiT-Tiny Hidden Dimension = 192.
// 我们假设每次计算处理一个 Tile 的 K 维度。
`define DEFAULT_K_DIM 192 

`endif

src/pe.v
// -----------------------------------------------------------------------------
// 文件名: pe.v
// 描述: Weight Stationary 处理单元
// 功能: 
//    1. Load Mode: 锁存权重 (reg_weight <= in_weight)
//    2. Compute Mode: out_psum = in_psum + (in_act * reg_weight)
//    3. Data Pass: 将输入 Activation 向右传递 (out_act <= in_act)
// -----------------------------------------------------------------------------

`include "/Users/wangsibo/program/deit_on_fpga/src/params.vh"

module pe (
    input  wire                     clk,
    input  wire                     rst_n,

    // --- 控制信号 ---
    // en_compute: 启用 MAC 运算 (流水线使能)
    // load_weight: 启用权重加载 (权重更新)
    input  wire                     en_compute,
    input  wire                     load_weight,

    // --- 数据通路 ---
    input  wire [`DATA_WIDTH-1:0]   in_act,    // 来自左侧 PE 的输入特征
    input  wire [`DATA_WIDTH-1:0]   in_weight, // 只有在 load_weight 有效时才使用
    input  wire [`ACC_WIDTH-1:0]    in_psum,   // 来自上方 PE 的部分和

    output reg  [`DATA_WIDTH-1:0]   out_act,   // 传递给右侧 PE
    output reg  [`ACC_WIDTH-1:0]    out_psum   // 传递给下方 PE
);

    // 内部权重寄存器
    reg signed [`DATA_WIDTH-1:0] reg_weight;

    // -------------------------------------------------------------------------
    // 核心逻辑
    // -------------------------------------------------------------------------
    always @(posedge clk or negedge rst_n) begin
        if (!rst_n) begin
            reg_weight <= 0;
            out_act    <= 0;
            out_psum   <= 0;
        end else begin
            // 1. 权重加载逻辑 (优先级高，或互斥)
            if (load_weight) begin
                reg_weight <= $signed(in_weight);
                // 在加载权重时，通常为了形成移位链，out_act 也可以用来传递权重
                // 但在本架构中，我们假设权重是单独加载或广播的，或者利用 act 路径
                // 这里为了简单，保持 act 通路清零或保持
            end

            // 2. 计算与数据传递逻辑
            if (en_compute) begin
                // Systolic Data Passing: 将输入特征打一拍传给右边
                out_act <= in_act;

                // MAC Operation: 乘加运算
                // 关键点: 必须使用 $signed 确保综合为有符号乘法
                // Zynq DSP48E1 支持 (A*B+C) 的单周期完成
                out_psum <= $signed(in_psum) + ($signed(in_act) * reg_weight);
            end
        end
    end

endmodule

src/pe_tb.v
// -----------------------------------------------------------------------------
// 文件名: pe_tb.v
// 描述: 验证单个 PE 的功能 (Checkpoint 2)
// 运行: iverilog -o pe_sim.out params.vh pe.v pe_tb.v && vvp pe_sim.out
// -----------------------------------------------------------------------------

`timescale 1ns / 1ps
`include "/Users/wangsibo/program/deit_on_fpga/src/params.vh"
module pe_tb;

    reg clk;
    reg rst_n;
    reg en_compute;
    reg load_weight;
    reg [`DATA_WIDTH-1:0] in_act;
    reg [`DATA_WIDTH-1:0] in_weight;
    reg [`ACC_WIDTH-1:0]  in_psum;

    wire [`DATA_WIDTH-1:0] out_act;
    wire [`ACC_WIDTH-1:0]  out_psum;

    // 实例化 PE
    pe dut (
        .clk(clk),
        .rst_n(rst_n),
        .en_compute(en_compute),
        .load_weight(load_weight),
        .in_act(in_act),
        .in_weight(in_weight),
        .in_psum(in_psum),
        .out_act(out_act),
        .out_psum(out_psum)
    );

    always #5 clk = ~clk;

    initial begin
        $dumpfile("pe_check.vcd");
        $dumpvars(0, pe_tb);

        // 初始化
        clk = 0; rst_n = 0;
        en_compute = 0; load_weight = 0;
        in_act = 0; in_weight = 0; in_psum = 0;

        #20 rst_n = 1;

        // ---------------------------------------------------------------------
        // Case 1: 加载权重 (Weight = 5)
        // ---------------------------------------------------------------------
        $display("--- Test Case 1: Load Weight = 5 ---");
        #10;
        load_weight = 1;
        in_weight = 8'd5;
        #10; // 等待时钟上升沿锁存
        load_weight = 0;
        in_weight = 0; // 清除输入，证明 PE 用的是内部锁存的 5

        // ---------------------------------------------------------------------
        // Case 2: 计算正数乘法 (Input = 10, Psum_In = 20)
        // 预期: Out = 20 + (10 * 5) = 70
        // ---------------------------------------------------------------------
        $display("--- Test Case 2: Positive Calc (10 * 5 + 20) ---");
        en_compute = 1;
        in_act = 8'd10;
        in_psum = 32'd20;
        #10; // 等待计算完成
        
        if (out_psum === 70) 
            $display("PASS: 20 + 10*5 = %d", out_psum);
        else 
            $display("FAIL: Expected 70, Got %d", out_psum);

        // ---------------------------------------------------------------------
        // Case 3: 计算负数乘法 (Input = -3, Psum_In = 100)
        // INT8: -3 的补码是 8'b11111101 (0xFD)
        // 预期: Out = 100 + (-3 * 5) = 100 - 15 = 85
        // ---------------------------------------------------------------------
        $display("--- Test Case 3: Negative Calc (-3 * 5 + 100) ---");
        in_act = -3; // Verilog 会自动处理补码，但需注意位宽
        in_psum = 32'd100;
        #10;

        if (out_psum === 85) 
            $display("PASS: 100 + (-3)*5 = %d", out_psum);
        else 
            $display("FAIL: Expected 85, Got %d", out_psum);

        // ---------------------------------------------------------------------
        // Case 4: 验证数据传递 (Data Passing)
        // ---------------------------------------------------------------------
        $display("--- Test Case 4: Data Passing ---");
        // 上一拍输入的 -3 应该在这一拍出现在 out_act
        if (out_act === -3 || out_act === 8'hFD)
            $display("PASS: out_act passed correctly.");
        else
            $display("FAIL: out_act not propagating.");

        $finish;
    end

endmodule

src/pe_check.vcd
$date
	Fri Jan  9 22:48:34 2026
$end
$version
	Icarus Verilog
$end
$timescale
	1ps
$end
$scope module pe_tb $end
$var wire 32 ! out_psum [31:0] $end
$var wire 8 " out_act [7:0] $end
$var reg 1 # clk $end
$var reg 1 $ en_compute $end
$var reg 8 % in_act [7:0] $end
$var reg 32 & in_psum [31:0] $end
$var reg 8 ' in_weight [7:0] $end
$var reg 1 ( load_weight $end
$var reg 1 ) rst_n $end
$scope module dut $end
$var wire 1 # clk $end
$var wire 1 $ en_compute $end
$var wire 8 * in_act [7:0] $end
$var wire 32 + in_psum [31:0] $end
$var wire 8 , in_weight [7:0] $end
$var wire 1 ( load_weight $end
$var wire 1 ) rst_n $end
$var reg 8 - out_act [7:0] $end
$var reg 32 . out_psum [31:0] $end
$var reg 8 / reg_weight [7:0] $end
$upscope $end
$upscope $end
$enddefinitions $end
$comment Show the parameter values. $end
$dumpall
$end
#0
$dumpvars
b0 /
b0 .
b0 -
b0 ,
b0 +
b0 *
0)
0(
b0 '
b0 &
b0 %
0$
0#
b0 "
b0 !
$end
#5000
1#
#10000
0#
#15000
1#
#20000
0#
1)
#25000
1#
#30000
0#
b101 '
b101 ,
1(
#35000
b101 /
1#
#40000
0#
b10100 &
b10100 +
b1010 %
b1010 *
1$
b0 '
b0 ,
0(
#45000
b1000110 !
b1000110 .
b1010 "
b1010 -
1#
#50000
0#
b1100100 &
b1100100 +
b11111101 %
b11111101 *
#55000
b1010101 !
b1010101 .
b11111101 "
b11111101 -
1#
